{
"result":{
"query":":facetid:toc:db\"/\"conf\"/\"uist\"/\"uist2011\".\"bht",
"status":{
"@code":"200",
"text":"OK"
},
"time":{
"@unit":"msecs",
"text":"104.77"
},
"completions":{
"@total":"1",
"@computed":"1",
"@sent":"1",
"c":{
"@sc":"70",
"@dc":"70",
"@oc":"70",
"@id":"17589993",
"text":":facetid:toc:db/conf/uist/uist2011.bht"
}
},
"hits":{
"@total":"70",
"@computed":"70",
"@sent":"70",
"@first":"0",
"hit":[{
"@score":"1",
"@id":"3109475",
"info":{"authors":{"author":[{"@pid":"20/9544","text":"Salman Ahmad"},{"@pid":"75/5304","text":"Alexis Battle"},{"@pid":"77/10299","text":"Zahan Malkani"},{"@pid":"53/5004","text":"Sepandar D. Kamvar"}]},"title":"The jabberwocky programming environment for structured social computing.","venue":"UIST","pages":"53-64","year":"2011","type":"Conference and Workshop Papers","key":"conf/uist/AhmadBMK11","doi":"10.1145/2047196.2047203","ee":"https://doi.org/10.1145/2047196.2047203","url":"https://dblp.org/rec/conf/uist/AhmadBMK11"},
"url":"URL#3109475"
},
{
"@score":"1",
"@id":"3109478",
"info":{"authors":{"author":[{"@pid":"76/2498","text":"Michelle Annett"},{"@pid":"19/114","text":"Tovi Grossman"},{"@pid":"w/DanielWigdor","text":"Daniel Wigdor"},{"@pid":"01/5804","text":"George W. Fitzmaurice"}]},"title":"Medusa - a proximity-aware multi-touch tabletop.","venue":"UIST","pages":"337-346","year":"2011","type":"Conference and Workshop Papers","key":"conf/uist/AnnettGWF11","doi":"10.1145/2047196.2047240","ee":"https://doi.org/10.1145/2047196.2047240","url":"https://dblp.org/rec/conf/uist/AnnettGWF11"},
"url":"URL#3109478"
},
{
"@score":"1",
"@id":"3109479",
"info":{"authors":{"author":[{"@pid":"30/4949","text":"Daniel Avrahami"},{"@pid":"18/6907","text":"Jacob O. Wobbrock"},{"@pid":"i/ShahramIzadi","text":"Shahram Izadi"}]},"title":"Portico - tangible interaction on and around a tablet.","venue":"UIST","pages":"347-356","year":"2011","type":"Conference and Workshop Papers","key":"conf/uist/AvrahamiWI11","doi":"10.1145/2047196.2047241","ee":"https://doi.org/10.1145/2047196.2047241","url":"https://dblp.org/rec/conf/uist/AvrahamiWI11"},
"url":"URL#3109479"
},
{
"@score":"1",
"@id":"3109481",
"info":{"authors":{"author":[{"@pid":"48/2547","text":"Michael S. Bernstein"},{"@pid":"41/6065","text":"Joel Brandt"},{"@pid":"m/RobMiller","text":"Robert C. Miller"},{"@pid":"k/DavidRKarger","text":"David R. Karger"}]},"title":"Crowds in two seconds - enabling realtime crowd-powered interfaces.","venue":"UIST","pages":"33-42","year":"2011","type":"Conference and Workshop Papers","key":"conf/uist/BernsteinBMK11","doi":"10.1145/2047196.2047201","ee":"https://doi.org/10.1145/2047196.2047201","url":"https://dblp.org/rec/conf/uist/BernsteinBMK11"},
"url":"URL#3109481"
},
{
"@score":"1",
"@id":"3109485",
"info":{"authors":{"author":[{"@pid":"79/804","text":"Alex Butler"},{"@pid":"82/2289","text":"Otmar Hilliges"},{"@pid":"i/ShahramIzadi","text":"Shahram Izadi"},{"@pid":"h/SteveHodges","text":"Steve Hodges"},{"@pid":"53/415","text":"David Molyneaux"},{"@pid":"02/2170","text":"David Kim"},{"@pid":"98/10299","text":"Danny Kong"}]},"title":"Vermeer - direct interaction with a 360° viewable 3D display.","venue":"UIST","pages":"569-576","year":"2011","type":"Conference and Workshop Papers","key":"conf/uist/ButlerHIHMKK11","doi":"10.1145/2047196.2047271","ee":"https://doi.org/10.1145/2047196.2047271","url":"https://dblp.org/rec/conf/uist/ButlerHIHMKK11"},
"url":"URL#3109485"
},
{
"@score":"1",
"@id":"3109486",
"info":{"authors":{"author":[{"@pid":"15/4574","text":"Géry Casiez"},{"@pid":"95/2264","text":"Nicolas Roussel"}]},"title":"No more bricolage! - methods and tools to characterize, replicate and compare pointing transfer functions.","venue":"UIST","pages":"603-614","year":"2011","type":"Conference and Workshop Papers","key":"conf/uist/CasiezR11","doi":"10.1145/2047196.2047276","ee":"https://doi.org/10.1145/2047196.2047276","url":"https://dblp.org/rec/conf/uist/CasiezR11"},
"url":"URL#3109486"
},
{
"@score":"1",
"@id":"3109488",
"info":{"authors":{"author":[{"@pid":"45/1648","text":"Jessica R. Cauchard"},{"@pid":"09/2951","text":"Markus Löchtefeld"},{"@pid":"79/3435","text":"Pourang Irani"},{"@pid":"64/5708","text":"Johannes Schöning"},{"@pid":"k/AntonioKruger","text":"Antonio Krüger"},{"@pid":"92/2757","text":"Mike Fraser"},{"@pid":"s/SriramSubramanian","text":"Sriram Subramanian"}]},"title":"Visual separation in mobile multi-display environments.","venue":"UIST","pages":"451-460","year":"2011","type":"Conference and Workshop Papers","key":"conf/uist/CauchardLISKFS11","doi":"10.1145/2047196.2047256","ee":"https://doi.org/10.1145/2047196.2047256","url":"https://dblp.org/rec/conf/uist/CauchardLISKFS11"},
"url":"URL#3109488"
},
{
"@score":"1",
"@id":"3109490",
"info":{"authors":{"author":[{"@pid":"76/3254","text":"Tsung-Hsiang Chang"},{"@pid":"05/6465","text":"Tom Yeh"},{"@pid":"m/RobMiller","text":"Rob Miller 0001"}]},"title":"Associating the visual representation of user interfaces with their internal structures and metadata.","venue":"UIST","pages":"245-256","year":"2011","type":"Conference and Workshop Papers","key":"conf/uist/ChangYM11","doi":"10.1145/2047196.2047228","ee":"https://doi.org/10.1145/2047196.2047228","url":"https://dblp.org/rec/conf/uist/ChangYM11"},
"url":"URL#3109490"
},
{
"@score":"1",
"@id":"3109491",
"info":{"authors":{"author":[{"@pid":"84/10299","text":"Hiroshi Chigira"},{"@pid":"77/2839","text":"Atsuhiko Maeda"},{"@pid":"37/4531","text":"Minoru Kobayashi"}]},"title":"Area-based photo-plethysmographic sensing method for the surfaces of handheld devices.","venue":"UIST","pages":"499-508","year":"2011","type":"Conference and Workshop Papers","key":"conf/uist/ChigiraMK11","doi":"10.1145/2047196.2047262","ee":"https://doi.org/10.1145/2047196.2047262","url":"https://dblp.org/rec/conf/uist/ChigiraMK11"},
"url":"URL#3109491"
},
{
"@score":"1",
"@id":"3109493",
"info":{"authors":{"author":[{"@pid":"95/48","text":"Pierre Dragicevic"},{"@pid":"57/1739","text":"Stéphane Huot"},{"@pid":"60/5884","text":"Fanny Chevalier"}]},"title":"Animating from markup code to rendered documents and vice versa.","venue":"UIST","pages":"257-262","year":"2011","type":"Conference and Workshop Papers","key":"conf/uist/DragicevicHC11","doi":"10.1145/2047196.2047229","ee":"https://doi.org/10.1145/2047196.2047229","url":"https://dblp.org/rec/conf/uist/DragicevicHC11"},
"url":"URL#3109493"
},
{
"@score":"1",
"@id":"3109494",
"info":{"authors":{"author":[{"@pid":"e/JamesREagan","text":"James R. Eagan"},{"@pid":"00/2489","text":"Michel Beaudouin-Lafon"},{"@pid":"m/WendyEMackay","text":"Wendy E. Mackay"}]},"title":"Cracking the cocoa nut - user interface programming at runtime.","venue":"UIST","pages":"225-234","year":"2011","type":"Conference and Workshop Papers","key":"conf/uist/EaganBM11","doi":"10.1145/2047196.2047226","ee":"https://doi.org/10.1145/2047196.2047226","url":"https://dblp.org/rec/conf/uist/EaganBM11"},
"url":"URL#3109494"
},
{
"@score":"1",
"@id":"3109495",
"info":{"authors":{"author":[{"@pid":"69/7949","text":"Michael D. Ekstrand"},{"@pid":"l/WeiLi2","text":"Wei Li 0002"},{"@pid":"19/114","text":"Tovi Grossman"},{"@pid":"82/1420","text":"Justin Matejka"},{"@pid":"01/5804","text":"George W. Fitzmaurice"}]},"title":"Searching for software learning resources using application context.","venue":"UIST","pages":"195-204","year":"2011","type":"Conference and Workshop Papers","key":"conf/uist/EkstrandLGMF11","doi":"10.1145/2047196.2047220","ee":"https://doi.org/10.1145/2047196.2047220","url":"https://dblp.org/rec/conf/uist/EkstrandLGMF11"},
"url":"URL#3109495"
},
{
"@score":"1",
"@id":"3109496",
"info":{"authors":{"author":[{"@pid":"09/7075","text":"Jennifer Fernquist"},{"@pid":"19/114","text":"Tovi Grossman"},{"@pid":"01/5804","text":"George W. Fitzmaurice"}]},"title":"Sketch-sketch revolution - an engaging tutorial system for guided sketching and application learning.","venue":"UIST","pages":"373-382","year":"2011","type":"Conference and Workshop Papers","key":"conf/uist/FernquistGF11","doi":"10.1145/2047196.2047245","ee":"https://doi.org/10.1145/2047196.2047245","url":"https://dblp.org/rec/conf/uist/FernquistGF11"},
"url":"URL#3109496"
},
{
"@score":"1",
"@id":"3109498",
"info":{"authors":{"author":[{"@pid":"93/7981","text":"David R. Flatla"},{"@pid":"g/CarlGutwin","text":"Carl Gutwin"},{"@pid":"93/2134","text":"Lennart E. Nacke"},{"@pid":"07/4718","text":"Scott Bateman"},{"@pid":"40/5931","text":"Regan L. Mandryk"}]},"title":"Calibration games - making calibration tasks enjoyable by adding motivating game elements.","venue":"UIST","pages":"403-412","year":"2011","type":"Conference and Workshop Papers","key":"conf/uist/FlatlaGNBM11","doi":"10.1145/2047196.2047248","ee":"https://doi.org/10.1145/2047196.2047248","url":"https://dblp.org/rec/conf/uist/FlatlaGNBM11"},
"url":"URL#3109498"
},
{
"@score":"1",
"@id":"3109499",
"info":{"authors":{"author":[{"@pid":"98/3439","text":"Sean Follmer"},{"@pid":"46/3417","text":"Micah K. Johnson"},{"@pid":"73/143","text":"Edward H. Adelson"},{"@pid":"45/2605-1","text":"Hiroshi Ishii 0001"}]},"title":"deForm - an interactive malleable surface for capturing 2.5D arbitrary objects, tools and touch.","venue":"UIST","pages":"527-536","year":"2011","type":"Conference and Workshop Papers","key":"conf/uist/FollmerJAI11","doi":"10.1145/2047196.2047265","ee":"https://doi.org/10.1145/2047196.2047265","url":"https://dblp.org/rec/conf/uist/FollmerJAI11"},
"url":"URL#3109499"
},
{
"@score":"1",
"@id":"3109500",
"info":{"authors":{"author":[{"@pid":"60/863","text":"Adam Fourney"},{"@pid":"21/4772","text":"Richard Mann"},{"@pid":"56/3708","text":"Michael A. Terry"}]},"title":"Query-feature graphs - bridging user vocabulary and system functionality.","venue":"UIST","pages":"207-216","year":"2011","type":"Conference and Workshop Papers","key":"conf/uist/FourneyMT11","doi":"10.1145/2047196.2047224","ee":"https://doi.org/10.1145/2047196.2047224","url":"https://dblp.org/rec/conf/uist/FourneyMT11"},
"url":"URL#3109500"
},
{
"@score":"1",
"@id":"3109502",
"info":{"authors":{"author":[{"@pid":"42/4768","text":"Max Goldman"},{"@pid":"26/3925","text":"Greg Little"},{"@pid":"m/RobMiller","text":"Robert C. Miller"}]},"title":"Real-time collaborative coding in a web IDE.","venue":"UIST","pages":"155-164","year":"2011","type":"Conference and Workshop Papers","key":"conf/uist/GoldmanLM11","doi":"10.1145/2047196.2047215","ee":"https://doi.org/10.1145/2047196.2047215","url":"https://dblp.org/rec/conf/uist/GoldmanLM11"},
"url":"URL#3109502"
},
{
"@score":"1",
"@id":"3109504",
"info":{"authors":{"author":[{"@pid":"32/193","text":"Philip J. Guo"},{"@pid":"57/3823","text":"Sean Kandel"},{"@pid":"h/JosephMHellerstein","text":"Joseph M. Hellerstein"},{"@pid":"27/4508","text":"Jeffrey Heer"}]},"title":"Proactive wrangling - mixed-initiative end-user programming of data transformation scripts.","venue":"UIST","pages":"65-74","year":"2011","type":"Conference and Workshop Papers","key":"conf/uist/GuoKHH11","doi":"10.1145/2047196.2047205","ee":"https://doi.org/10.1145/2047196.2047205","url":"https://dblp.org/rec/conf/uist/GuoKHH11"},
"url":"URL#3109504"
},
{
"@score":"1",
"@id":"3109505",
"info":{"authors":{"author":[{"@pid":"79/3112","text":"Sean Gustafson"},{"@pid":"79/7439-1","text":"Christian Holz 0001"},{"@pid":"b/PatrickBaudisch","text":"Patrick Baudisch"}]},"title":"Imaginary phone - learning imaginary interfaces by transferring spatial memory from a familiar device.","venue":"UIST","pages":"283-292","year":"2011","type":"Conference and Workshop Papers","key":"conf/uist/GustafsonHB11","doi":"10.1145/2047196.2047233","ee":"https://doi.org/10.1145/2047196.2047233","url":"https://dblp.org/rec/conf/uist/GustafsonHB11"},
"url":"URL#3109505"
},
{
"@score":"1",
"@id":"3109506",
"info":{"authors":{"author":[{"@pid":"41/6185","text":"Martin Hachet"},{"@pid":"95/8693","text":"Benoît Bossavit"},{"@pid":"38/9544","text":"Aurélie Cohé"},{"@pid":"20/5273","text":"Jean-Baptiste de la Rivière"}]},"title":"Toucheo - multitouch and stereo combined in a seamless workspace.","venue":"UIST","pages":"587-592","year":"2011","type":"Conference and Workshop Papers","key":"conf/uist/HachetBCR11","doi":"10.1145/2047196.2047273","ee":"https://doi.org/10.1145/2047196.2047273","url":"https://dblp.org/rec/conf/uist/HachetBCR11"},
"url":"URL#3109506"
},
{
"@score":"1",
"@id":"3109508",
"info":{"authors":{"author":[{"@pid":"13/2537","text":"Sudheendra Hangal"},{"@pid":"l/MonicaSLam","text":"Monica S. Lam"},{"@pid":"27/4508","text":"Jeffrey Heer"}]},"title":"MUSE - reviving memories using email archives.","venue":"UIST","pages":"75-84","year":"2011","type":"Conference and Workshop Papers","key":"conf/uist/HangalLH11","doi":"10.1145/2047196.2047206","ee":"https://doi.org/10.1145/2047196.2047206","url":"https://dblp.org/rec/conf/uist/HangalLH11"},
"url":"URL#3109508"
},
{
"@score":"1",
"@id":"3109509",
"info":{"authors":{"author":[{"@pid":"77/2637","text":"Chris Harrison 0001"},{"@pid":"73/5679","text":"Hrvoje Benko"},{"@pid":"77/3558","text":"Andrew D. Wilson"}]},"title":"OmniTouch - wearable multitouch interaction everywhere.","venue":"UIST","pages":"441-450","year":"2011","type":"Conference and Workshop Papers","key":"conf/uist/HarrisonBW11","doi":"10.1145/2047196.2047255","ee":"https://doi.org/10.1145/2047196.2047255","url":"https://dblp.org/rec/conf/uist/HarrisonBW11"},
"url":"URL#3109509"
},
{
"@score":"1",
"@id":"3109510",
"info":{"authors":{"author":[{"@pid":"77/2637","text":"Chris Harrison 0001"},{"@pid":"h/ScottEHudson","text":"Scott E. Hudson"}]},"title":"A new angle on cheap LCDs - making positive use of optical distortion.","venue":"UIST","pages":"537-540","year":"2011","type":"Conference and Workshop Papers","key":"conf/uist/HarrisonH11","doi":"10.1145/2047196.2047266","ee":"https://doi.org/10.1145/2047196.2047266","url":"https://dblp.org/rec/conf/uist/HarrisonH11"},
"url":"URL#3109510"
},
{
"@score":"1",
"@id":"3109511",
"info":{"authors":{"author":[{"@pid":"77/2637","text":"Chris Harrison 0001"},{"@pid":"79/7045","text":"Julia Schwarz"},{"@pid":"h/ScottEHudson","text":"Scott E. Hudson"}]},"title":"TapSense - enhancing finger interaction on touch surfaces.","venue":"UIST","pages":"627-636","year":"2011","type":"Conference and Workshop Papers","key":"conf/uist/HarrisonSH11","doi":"10.1145/2047196.2047279","ee":"https://doi.org/10.1145/2047196.2047279","url":"https://dblp.org/rec/conf/uist/HarrisonSH11"},
"url":"URL#3109511"
},
{
"@score":"1",
"@id":"3109512",
"info":{"authors":{"author":[{"@pid":"81/7962","text":"Seongkook Heo"},{"@pid":"36/9541","text":"Jaehyun Han"},{"@pid":"89/9540","text":"Sangwon Choi"},{"@pid":"73/973","text":"Seunghwan Lee"},{"@pid":"70/570","text":"Geehyuk Lee"},{"@pid":"08/984","text":"Hyong-Euk Lee"},{"@pid":"94/10299","text":"SangHyun Kim"},{"@pid":"70/4553","text":"Won-Chul Bang"},{"@pid":"78/10299","text":"Do-Kyoon Kim"},{"@pid":"05/5366","text":"Changyeong Kim"}]},"title":"IrCube tracker - an optical 6-DOF tracker based on LED directivity.","venue":"UIST","pages":"577-586","year":"2011","type":"Conference and Workshop Papers","key":"conf/uist/HeoHCLLLKBKK11","doi":"10.1145/2047196.2047272","ee":"https://doi.org/10.1145/2047196.2047272","url":"https://dblp.org/rec/conf/uist/HeoHCLLLKBKK11"},
"url":"URL#3109512"
},
{
"@score":"1",
"@id":"3109513",
"info":{"authors":{"author":[{"@pid":"81/7962","text":"Seongkook Heo"},{"@pid":"70/570","text":"Geehyuk Lee"}]},"title":"Force gestures - augmenting touch screen gestures with normal and tangential forces.","venue":"UIST","pages":"621-626","year":"2011","type":"Conference and Workshop Papers","key":"conf/uist/HeoL11","doi":"10.1145/2047196.2047278","ee":"https://doi.org/10.1145/2047196.2047278","url":"https://dblp.org/rec/conf/uist/HeoL11"},
"url":"URL#3109513"
},
{
"@score":"1",
"@id":"3109514",
"info":{"authors":{"author":[{"@pid":"67/7984","text":"Juan David Hincapié-Ramos"},{"@pid":"97/1533","text":"Stephen Voida"},{"@pid":"17/1744","text":"Gloria Mark"}]},"title":"A design space analysis of availability-sharing systems.","venue":"UIST","pages":"85-96","year":"2011","type":"Conference and Workshop Papers","key":"conf/uist/Hincapie-RamosVM11","doi":"10.1145/2047196.2047207","ee":"https://doi.org/10.1145/2047196.2047207","url":"https://dblp.org/rec/conf/uist/Hincapie-RamosVM11"},
"url":"URL#3109514"
},
{
"@score":"1",
"@id":"3109518",
"info":{"authors":{"author":[{"@pid":"i/ShahramIzadi","text":"Shahram Izadi"},{"@pid":"02/2170","text":"David Kim"},{"@pid":"82/2289","text":"Otmar Hilliges"},{"@pid":"53/415","text":"David Molyneaux"},{"@pid":"01/8653","text":"Richard A. Newcombe"},{"@pid":"94/248","text":"Pushmeet Kohli"},{"@pid":"47/572","text":"Jamie Shotton"},{"@pid":"h/SteveHodges","text":"Steve Hodges"},{"@pid":"15/9958","text":"Dustin Freeman"},{"@pid":"d/AndrewJDavison","text":"Andrew J. Davison"},{"@pid":"f/AndrewWFitzgibbon","text":"Andrew W. Fitzgibbon"}]},"title":"KinectFusion - real-time 3D reconstruction and interaction using a moving depth camera.","venue":"UIST","pages":"559-568","year":"2011","type":"Conference and Workshop Papers","key":"conf/uist/IzadiKHMNKSHFDF11","doi":"10.1145/2047196.2047270","ee":"https://doi.org/10.1145/2047196.2047270","url":"https://dblp.org/rec/conf/uist/IzadiKHMNKSHFDF11"},
"url":"URL#3109518"
},
{
"@score":"1",
"@id":"3109519",
"info":{"authors":{"author":{"@pid":"31/985","text":"Dan Jurafsky"}},"title":"Sex, food, and words - the hidden meanings behind everyday language.","venue":"UIST","pages":"429-430","year":"2011","type":"Conference and Workshop Papers","key":"conf/uist/Jurafsky11","doi":"10.1145/2047196.2047252","ee":"https://doi.org/10.1145/2047196.2047252","url":"https://dblp.org/rec/conf/uist/Jurafsky11"},
"url":"URL#3109519"
},
{
"@score":"1",
"@id":"3109520",
"info":{"authors":{"author":[{"@pid":"63/6371","text":"Shaun K. Kane"},{"@pid":"m/MeredithRingelMorris","text":"Meredith Ringel Morris"},{"@pid":"07/6812","text":"Annuska Z. Perkins"},{"@pid":"w/DanielWigdor","text":"Daniel Wigdor"},{"@pid":"l/RELadner","text":"Richard E. Ladner"},{"@pid":"18/6907","text":"Jacob O. Wobbrock"}]},"title":"Access overlays - improving non-visual access to large touch screens for blind users.","venue":"UIST","pages":"273-282","year":"2011","type":"Conference and Workshop Papers","key":"conf/uist/KaneMPWLW11","doi":"10.1145/2047196.2047232","ee":"https://doi.org/10.1145/2047196.2047232","url":"https://dblp.org/rec/conf/uist/KaneMPWLW11"},
"url":"URL#3109520"
},
{
"@score":"1",
"@id":"3109522",
"info":{"authors":{"author":[{"@pid":"25/1030","text":"Thorsten Karrer"},{"@pid":"04/7986","text":"Jan-Peter Krämer"},{"@pid":"73/3985","text":"Jonathan Diehl"},{"@pid":"92/443","text":"Björn Hartmann"},{"@pid":"b/JOBorchers","text":"Jan O. Borchers"}]},"title":"Stacksplorer - call graph navigation helps increasing code maintenance efficiency.","venue":"UIST","pages":"217-224","year":"2011","type":"Conference and Workshop Papers","key":"conf/uist/KarrerKDHB11","doi":"10.1145/2047196.2047225","ee":"https://doi.org/10.1145/2047196.2047225","url":"https://dblp.org/rec/conf/uist/KarrerKDHB11"},
"url":"URL#3109522"
},
{
"@score":"1",
"@id":"3109523",
"info":{"authors":{"author":[{"@pid":"81/872","text":"Aniket Kittur"},{"@pid":"10/7984","text":"Boris Smus"},{"@pid":"19/10300","text":"Susheel Khamkar"},{"@pid":"k/RobertEKraut","text":"Robert E. Kraut"}]},"title":"CrowdForge - crowdsourcing complex work.","venue":"UIST","pages":"43-52","year":"2011","type":"Conference and Workshop Papers","key":"conf/uist/KitturSKK11","doi":"10.1145/2047196.2047202","ee":"https://doi.org/10.1145/2047196.2047202","url":"https://dblp.org/rec/conf/uist/KitturSKK11"},
"url":"URL#3109523"
},
{
"@score":"1",
"@id":"3109526",
"info":{"authors":{"author":[{"@pid":"04/10300","text":"Walter S. Lasecki"},{"@pid":"93/8732","text":"Kyle I. Murray"},{"@pid":"50/8735","text":"Samuel White"},{"@pid":"m/RobMiller","text":"Robert C. Miller"},{"@pid":"83/6818","text":"Jeffrey P. Bigham"}]},"title":"Real-time crowd control of existing interfaces.","venue":"UIST","pages":"23-32","year":"2011","type":"Conference and Workshop Papers","key":"conf/uist/LaseckiMWMB11","doi":"10.1145/2047196.2047200","ee":"https://doi.org/10.1145/2047196.2047200","url":"https://dblp.org/rec/conf/uist/LaseckiMWMB11"},
"url":"URL#3109526"
},
{
"@score":"1",
"@id":"3109528",
"info":{"authors":{"author":[{"@pid":"56/7555","text":"Jinha Lee"},{"@pid":"11/666","text":"Rehmi Post"},{"@pid":"45/2605-1","text":"Hiroshi Ishii 0001"}]},"title":"ZeroN - mid-air tangible interaction enabled by computer controlled magnetic levitation.","venue":"UIST","pages":"327-336","year":"2011","type":"Conference and Workshop Papers","key":"conf/uist/LeePI11","doi":"10.1145/2047196.2047239","ee":"https://doi.org/10.1145/2047196.2047239","url":"https://dblp.org/rec/conf/uist/LeePI11"},
"url":"URL#3109528"
},
{
"@score":"1",
"@id":"3109529",
"info":{"authors":{"author":[{"@pid":"95/1908","text":"Daniel Leithinger"},{"@pid":"58/9599","text":"David Lakatos"},{"@pid":"93/9308","text":"Anthony DeVincenzi"},{"@pid":"13/9597","text":"Matthew Blackshaw"},{"@pid":"45/2605-1","text":"Hiroshi Ishii 0001"}]},"title":"Direct and gestural interaction with relief - a 2.5D shape display.","venue":"UIST","pages":"541-548","year":"2011","type":"Conference and Workshop Papers","key":"conf/uist/LeithingerLDBI11","doi":"10.1145/2047196.2047268","ee":"https://doi.org/10.1145/2047196.2047268","url":"https://dblp.org/rec/conf/uist/LeithingerLDBI11"},
"url":"URL#3109529"
},
{
"@score":"1",
"@id":"3109530",
"info":{"authors":{"author":[{"@pid":"68/5440","text":"Jakob Leitner"},{"@pid":"h/MichaelHaller","text":"Michael Haller"}]},"title":"Harpoon selection - efficient selections for ungrouped content on large pen-based surfaces.","venue":"UIST","pages":"593-602","year":"2011","type":"Conference and Workshop Papers","key":"conf/uist/LeitnerH11","doi":"10.1145/2047196.2047275","ee":"https://doi.org/10.1145/2047196.2047275","url":"https://dblp.org/rec/conf/uist/LeitnerH11"},
"url":"URL#3109530"
},
{
"@score":"1",
"@id":"3109531",
"info":{"authors":{"author":[{"@pid":"l/WeiLi2","text":"Wei Li 0002"},{"@pid":"19/114","text":"Tovi Grossman"},{"@pid":"82/1420","text":"Justin Matejka"},{"@pid":"01/5804","text":"George W. Fitzmaurice"}]},"title":"TwitApp - in-product micro-blogging for design sharing.","venue":"UIST","pages":"185-194","year":"2011","type":"Conference and Workshop Papers","key":"conf/uist/LiGMF11","doi":"10.1145/2047196.2047219","ee":"https://doi.org/10.1145/2047196.2047219","url":"https://dblp.org/rec/conf/uist/LiGMF11"},
"url":"URL#3109531"
},
{
"@score":"1",
"@id":"3109532",
"info":{"authors":{"author":[{"@pid":"21/7438","text":"Frank Chun Yat Li"},{"@pid":"49/9298","text":"Richard T. Guy"},{"@pid":"71/5014","text":"Koji Yatani"},{"@pid":"31/5694","text":"Khai N. Truong"}]},"title":"The 1line keyboard - a QWERTY layout in a single line.","venue":"UIST","pages":"461-470","year":"2011","type":"Conference and Workshop Papers","key":"conf/uist/LiGYT11","doi":"10.1145/2047196.2047257","ee":"https://doi.org/10.1145/2047196.2047257","url":"https://dblp.org/rec/conf/uist/LiGYT11"},
"url":"URL#3109532"
},
{
"@score":"1",
"@id":"3109534",
"info":{"authors":{"author":[{"@pid":"02/9170","text":"Felix Xiaozhu Lin"},{"@pid":"74/5481","text":"Daniel Ashbrook"},{"@pid":"08/6508","text":"Sean White"}]},"title":"RhythmLink - securely pairing I/O-constrained devices by tapping.","venue":"UIST","pages":"263-272","year":"2011","type":"Conference and Workshop Papers","key":"conf/uist/LinAW11","doi":"10.1145/2047196.2047231","ee":"https://doi.org/10.1145/2047196.2047231","url":"https://dblp.org/rec/conf/uist/LinAW11"},
"url":"URL#3109534"
},
{
"@score":"1",
"@id":"3109535",
"info":{"authors":{"author":[{"@pid":"71/10299","text":"Shu-Yang Lin"},{"@pid":"14/10300","text":"Chao-Huai Su"},{"@pid":"74/6672","text":"Kai-Yin Cheng"},{"@pid":"14/7599","text":"Rong-Hao Liang"},{"@pid":"11/8319","text":"Tzu-Hao Kuo"},{"@pid":"72/6720","text":"Bing-Yu Chen"}]},"title":"Pub - point upon body - exploring eyes-free interaction and methods on an arm.","venue":"UIST","pages":"481-488","year":"2011","type":"Conference and Workshop Papers","key":"conf/uist/LinSCLKC11","doi":"10.1145/2047196.2047259","ee":"https://doi.org/10.1145/2047196.2047259","url":"https://dblp.org/rec/conf/uist/LinSCLKC11"},
"url":"URL#3109535"
},
{
"@score":"1",
"@id":"3109537",
"info":{"authors":{"author":[{"@pid":"m/IScottMacKenzie","text":"I. Scott MacKenzie"},{"@pid":"36/3779","text":"R. William Soukoreff"},{"@pid":"06/10300","text":"Joanna Helga"}]},"title":"1 thumb, 4 buttons, 20 words per minute - design and evaluation of H4-writer.","venue":"UIST","pages":"471-480","year":"2011","type":"Conference and Workshop Papers","key":"conf/uist/MacKenzieSH11","doi":"10.1145/2047196.2047258","ee":"https://doi.org/10.1145/2047196.2047258","url":"https://dblp.org/rec/conf/uist/MacKenzieSH11"},
"url":"URL#3109537"
},
{
"@score":"1",
"@id":"3109538",
"info":{"authors":{"author":[{"@pid":"34/1905","text":"Hiroyuki Manabe"},{"@pid":"49/6475","text":"Masaaki Fukumoto"}]},"title":"Tap control for headphones without sensors.","venue":"UIST","pages":"309-314","year":"2011","type":"Conference and Workshop Papers","key":"conf/uist/ManabeF11","doi":"10.1145/2047196.2047236","ee":"https://doi.org/10.1145/2047196.2047236","url":"https://dblp.org/rec/conf/uist/ManabeF11"},
"url":"URL#3109538"
},
{
"@score":"1",
"@id":"3109539",
"info":{"authors":{"author":[{"@pid":"38/166","text":"Nicolai Marquardt"},{"@pid":"79/7984","text":"Robert Diaz-Marino"},{"@pid":"50/6403","text":"Sebastian Boring"},{"@pid":"g/SaulGreenberg","text":"Saul Greenberg"}]},"title":"The proximity toolkit - prototyping proxemic interactions in ubiquitous computing ecologies.","venue":"UIST","pages":"315-326","year":"2011","type":"Conference and Workshop Papers","key":"conf/uist/MarquardtDBG11","doi":"10.1145/2047196.2047238","ee":"https://doi.org/10.1145/2047196.2047238","url":"https://dblp.org/rec/conf/uist/MarquardtDBG11"},
"url":"URL#3109539"
},
{
"@score":"1",
"@id":"3109540",
"info":{"authors":{"author":[{"@pid":"82/1420","text":"Justin Matejka"},{"@pid":"19/114","text":"Tovi Grossman"},{"@pid":"01/5804","text":"George W. Fitzmaurice"}]},"title":"IP-QAT - in-product questions, answers, &amp; tips.","venue":"UIST","pages":"175-184","year":"2011","type":"Conference and Workshop Papers","key":"conf/uist/MatejkaGF11","doi":"10.1145/2047196.2047218","ee":"https://doi.org/10.1145/2047196.2047218","url":"https://dblp.org/rec/conf/uist/MatejkaGF11"},
"url":"URL#3109540"
},
{
"@score":"1",
"@id":"3109541",
"info":{"authors":{"author":[{"@pid":"14/96","text":"Neema Moraveji"},{"@pid":"72/10299","text":"Ben Olson"},{"@pid":"02/9600","text":"Truc Nguyen"},{"@pid":"17/10300","text":"Mahmoud Saadat"},{"@pid":"71/4027","text":"Yaser Khalighi"},{"@pid":"44/2996","text":"Roy Pea"},{"@pid":"27/4508","text":"Jeffrey Heer"}]},"title":"Peripheral paced respiration - influencing user physiology during information work.","venue":"UIST","pages":"423-428","year":"2011","type":"Conference and Workshop Papers","key":"conf/uist/MoravejiONSKPH11","doi":"10.1145/2047196.2047250","ee":"https://doi.org/10.1145/2047196.2047250","url":"https://dblp.org/rec/conf/uist/MoravejiONSKPH11"},
"url":"URL#3109541"
},
{
"@score":"1",
"@id":"3109543",
"info":{"authors":{"author":[{"@pid":"81/10299","text":"Jon Noronha"},{"@pid":"95/10299","text":"Eric Hysen"},{"@pid":"65/7161","text":"Haoqi Zhang"},{"@pid":"g/KrzysztofZGajos","text":"Krzysztof Z. Gajos"}]},"title":"Platemate - crowdsourcing nutritional analysis from food photographs.","venue":"UIST","pages":"1-12","year":"2011","type":"Conference and Workshop Papers","key":"conf/uist/NoronhaHZG11","doi":"10.1145/2047196.2047198","ee":"https://doi.org/10.1145/2047196.2047198","url":"https://dblp.org/rec/conf/uist/NoronhaHZG11"},
"url":"URL#3109543"
},
{
"@score":"1",
"@id":"3109544",
"info":{"authors":{"author":[{"@pid":"p/APaepcke","text":"Andreas Paepcke"},{"@pid":"93/10299","text":"Bianca Soto"},{"@pid":"56/1315","text":"Leila Takayama"},{"@pid":"13/10300","text":"Frank Koenig"},{"@pid":"08/179","text":"Blaise Gassend"}]},"title":"Yelling in the hall - using sidetone to address a problem with mobile remote presence systems.","venue":"UIST","pages":"107-116","year":"2011","type":"Conference and Workshop Papers","key":"conf/uist/PaepckeSTKG11","doi":"10.1145/2047196.2047209","ee":"https://doi.org/10.1145/2047196.2047209","url":"https://dblp.org/rec/conf/uist/PaepckeSTKG11"},
"url":"URL#3109544"
},
{
"@score":"1",
"@id":"3109550",
"info":{"authors":{"author":[{"@pid":"30/393","text":"Suporn Pongnumkul"},{"@pid":"24/425","text":"Mira Dontcheva"},{"@pid":"36/4520","text":"Wilmot Li"},{"@pid":"69/393-1","text":"Jue Wang 0001"},{"@pid":"52/546","text":"Lubomir D. Bourdev"},{"@pid":"02/617","text":"Shai Avidan"},{"@pid":"07/1994","text":"Michael F. Cohen"}]},"title":"Pause-and-play - automatically linking screencast video tutorials with applications.","venue":"UIST","pages":"135-144","year":"2011","type":"Conference and Workshop Papers","key":"conf/uist/PongnumkulDLWBAC11","doi":"10.1145/2047196.2047213","ee":"https://doi.org/10.1145/2047196.2047213","url":"https://dblp.org/rec/conf/uist/PongnumkulDLWBAC11"},
"url":"URL#3109550"
},
{
"@score":"1",
"@id":"3109552",
"info":{"authors":{"author":[{"@pid":"82/10299","text":"Vidya Ramesh"},{"@pid":"07/10300","text":"Charlie Hsu"},{"@pid":"64/2431","text":"Maneesh Agrawala"},{"@pid":"92/443","text":"Björn Hartmann"}]},"title":"ShowMeHow - translating user interface instructions between applications.","venue":"UIST","pages":"127-134","year":"2011","type":"Conference and Workshop Papers","key":"conf/uist/RameshHAH11","doi":"10.1145/2047196.2047212","ee":"https://doi.org/10.1145/2047196.2047212","url":"https://dblp.org/rec/conf/uist/RameshHAH11"},
"url":"URL#3109552"
},
{
"@score":"1",
"@id":"3109555",
"info":{"authors":{"author":[{"@pid":"17/7188","text":"Daniel Ritchie"},{"@pid":"05/10300","text":"Ankita Arvind Kejriwal"},{"@pid":"97/4414","text":"Scott R. Klemmer"}]},"title":"d.tour - style-based exploration of design example galleries.","venue":"UIST","pages":"165-174","year":"2011","type":"Conference and Workshop Papers","key":"conf/uist/RitchieKK11","doi":"10.1145/2047196.2047216","ee":"https://doi.org/10.1145/2047196.2047216","url":"https://dblp.org/rec/conf/uist/RitchieKK11"},
"url":"URL#3109555"
},
{
"@score":"1",
"@id":"3109557",
"info":{"authors":{"author":[{"@pid":"12/10300","text":"Sonja Rümelin"},{"@pid":"94/6884","text":"Enrico Rukzio"},{"@pid":"79/2589","text":"Robert Hardy"}]},"title":"NaviRadar - a novel tactile information display for pedestrian navigation.","venue":"UIST","pages":"293-302","year":"2011","type":"Conference and Workshop Papers","key":"conf/uist/RumelinRH11","doi":"10.1145/2047196.2047234","ee":"https://doi.org/10.1145/2047196.2047234","url":"https://dblp.org/rec/conf/uist/RumelinRH11"},
"url":"URL#3109557"
},
{
"@score":"1",
"@id":"3109558",
"info":{"authors":{"author":[{"@pid":"18/10300","text":"Jeffrey M. Rzeszotarski"},{"@pid":"81/872","text":"Aniket Kittur"}]},"title":"Instrumenting the crowd - using implicit behavioral measures to predict task performance.","venue":"UIST","pages":"13-22","year":"2011","type":"Conference and Workshop Papers","key":"conf/uist/RzeszotarskiK11","doi":"10.1145/2047196.2047199","ee":"https://doi.org/10.1145/2047196.2047199","url":"https://dblp.org/rec/conf/uist/RzeszotarskiK11"},
"url":"URL#3109558"
},
{
"@score":"1",
"@id":"3109559",
"info":{"authors":{"author":[{"@pid":"05/2451","text":"T. Scott Saponas"},{"@pid":"77/2637","text":"Chris Harrison 0001"},{"@pid":"73/5679","text":"Hrvoje Benko"}]},"title":"PocketTouch - through-fabric capacitive touch input.","venue":"UIST","pages":"303-308","year":"2011","type":"Conference and Workshop Papers","key":"conf/uist/SaponasHB11","doi":"10.1145/2047196.2047235","ee":"https://doi.org/10.1145/2047196.2047235","url":"https://dblp.org/rec/conf/uist/SaponasHB11"},
"url":"URL#3109559"
},
{
"@score":"1",
"@id":"3109560",
"info":{"authors":{"author":[{"@pid":"21/9924","text":"Manolis Savva"},{"@pid":"00/1560","text":"Nicholas Kong"},{"@pid":"09/10300","text":"Arti Chhajta"},{"@pid":"79/2528","text":"Fei-Fei Li 0001"},{"@pid":"64/2431","text":"Maneesh Agrawala"},{"@pid":"27/4508","text":"Jeffrey Heer"}]},"title":"ReVision - automated classification, analysis and redesign of chart images.","venue":"UIST","pages":"393-402","year":"2011","type":"Conference and Workshop Papers","key":"conf/uist/SavvaKCFAH11","doi":"10.1145/2047196.2047247","ee":"https://doi.org/10.1145/2047196.2047247","url":"https://dblp.org/rec/conf/uist/SavvaKCFAH11"},
"url":"URL#3109560"
},
{
"@score":"1",
"@id":"3109561",
"info":{"authors":{"author":[{"@pid":"79/7045","text":"Julia Schwarz"},{"@pid":"84/6721","text":"Jennifer Mankoff"},{"@pid":"h/ScottEHudson","text":"Scott E. Hudson"}]},"title":"Monte carlo methods for managing interactive state, action and feedback under uncertainty.","venue":"UIST","pages":"235-244","year":"2011","type":"Conference and Workshop Papers","key":"conf/uist/SchwarzMH11","doi":"10.1145/2047196.2047227","ee":"https://doi.org/10.1145/2047196.2047227","url":"https://dblp.org/rec/conf/uist/SchwarzMH11"},
"url":"URL#3109561"
},
{
"@score":"1",
"@id":"3109563",
"info":{"authors":{"author":[{"@pid":"66/9117","text":"Ronit Slyper"},{"@pid":"03/2381","text":"Jill Fain Lehman"},{"@pid":"46/4227","text":"Jodi Forlizzi"},{"@pid":"75/3852","text":"Jessica K. Hodgins"}]},"title":"A tongue input device for creating conversations.","venue":"UIST","pages":"117-126","year":"2011","type":"Conference and Workshop Papers","key":"conf/uist/SlyperLFH11","doi":"10.1145/2047196.2047210","ee":"https://doi.org/10.1145/2047196.2047210","url":"https://dblp.org/rec/conf/uist/SlyperLFH11"},
"url":"URL#3109563"
},
{
"@score":"1",
"@id":"3109565",
"info":{"authors":{"author":[{"@pid":"83/7556","text":"Yuta Sugiura"},{"@pid":"80/7598","text":"Kakehi Gota"},{"@pid":"76/7597","text":"Anusha I. Withana"},{"@pid":"08/10300","text":"Calista Lee"},{"@pid":"01/844","text":"Daisuke Sakamoto"},{"@pid":"33/3150","text":"Maki Sugimoto"},{"@pid":"90/1139","text":"Masahiko Inami"},{"@pid":"03/6674","text":"Takeo Igarashi"}]},"title":"Detecting shape deformation of soft objects using directional photoreflectivity measurement.","venue":"UIST","pages":"509-516","year":"2011","type":"Conference and Workshop Papers","key":"conf/uist/SugiuraGWLSSII11","doi":"10.1145/2047196.2047263","ee":"https://doi.org/10.1145/2047196.2047263","url":"https://dblp.org/rec/conf/uist/SugiuraGWLSSII11"},
"url":"URL#3109565"
},
{
"@score":"1",
"@id":"3109566",
"info":{"authors":{"author":[{"@pid":"54/813","text":"Yuki Takahashi"},{"@pid":"14/6430","text":"Hiroaki Kojima"},{"@pid":"45/2122","text":"Ken-ichi Okada"}]},"title":"Injured person information management during second triage.","venue":"UIST","pages":"97-106","year":"2011","type":"Conference and Workshop Papers","key":"conf/uist/TakahashiKO11","doi":"10.1145/2047196.2047208","ee":"https://doi.org/10.1145/2047196.2047208","url":"https://dblp.org/rec/conf/uist/TakahashiKO11"},
"url":"URL#3109566"
},
{
"@score":"1",
"@id":"3109568",
"info":{"authors":{"author":[{"@pid":"15/10300","text":"Yannick Thiel"},{"@pid":"00/505","text":"Karan Singh"},{"@pid":"73/5426","text":"Ravin Balakrishnan"}]},"title":"Elasticurves - exploiting stroke dynamics and inertia for the real-time neatening of sketched 2D curves.","venue":"UIST","pages":"383-392","year":"2011","type":"Conference and Workshop Papers","key":"conf/uist/ThielSB11","doi":"10.1145/2047196.2047246","ee":"https://doi.org/10.1145/2047196.2047246","url":"https://dblp.org/rec/conf/uist/ThielSB11"},
"url":"URL#3109568"
},
{
"@score":"1",
"@id":"3109569",
"info":{"authors":{"author":[{"@pid":"59/838","text":"Daniel Vogel 0001"},{"@pid":"15/4574","text":"Géry Casiez"}]},"title":"Conté - multimodal input inspired by an artist&apos;s crayon.","venue":"UIST","pages":"357-366","year":"2011","type":"Conference and Workshop Papers","key":"conf/uist/VogelC11","doi":"10.1145/2047196.2047242","ee":"https://doi.org/10.1145/2047196.2047242","url":"https://dblp.org/rec/conf/uist/VogelC11"},
"url":"URL#3109569"
},
{
"@score":"1",
"@id":"3109570",
"info":{"authors":{"author":{"@pid":"34/5591-2","text":"Ge Wang 0002"}},"title":"Breaking barriers with sound.","venue":"UIST","pages":"205-206","year":"2011","type":"Conference and Workshop Papers","key":"conf/uist/Wang11","doi":"10.1145/2047196.2047222","ee":"https://doi.org/10.1145/2047196.2047222","url":"https://dblp.org/rec/conf/uist/Wang11"},
"url":"URL#3109570"
},
{
"@score":"1",
"@id":"3109571",
"info":{"authors":{"author":[{"@pid":"99/3230","text":"Robert Y. Wang"},{"@pid":"p/SylvainParis","text":"Sylvain Paris"},{"@pid":"p/JovanPopovic","text":"Jovan Popovic"}]},"title":"6D hands - markerless hand-tracking for computer aided design.","venue":"UIST","pages":"549-558","year":"2011","type":"Conference and Workshop Papers","key":"conf/uist/WangPP11","doi":"10.1145/2047196.2047269","ee":"https://doi.org/10.1145/2047196.2047269","url":"https://dblp.org/rec/conf/uist/WangPP11"},
"url":"URL#3109571"
},
{
"@score":"1",
"@id":"3109572",
"info":{"authors":{"author":[{"@pid":"34/5723","text":"Malte Weiss"},{"@pid":"80/9542","text":"Chat Wacharamanotham"},{"@pid":"91/9957","text":"Simon Voelker"},{"@pid":"b/JOBorchers","text":"Jan O. Borchers"}]},"title":"FingerFlux - near-surface haptic feedback on tabletops.","venue":"UIST","pages":"615-620","year":"2011","type":"Conference and Workshop Papers","key":"conf/uist/WeissWVB11","doi":"10.1145/2047196.2047277","ee":"https://doi.org/10.1145/2047196.2047277","url":"https://dblp.org/rec/conf/uist/WeissWVB11"},
"url":"URL#3109572"
},
{
"@score":"1",
"@id":"3109574",
"info":{"authors":{"author":[{"@pid":"82/121","text":"Karl D. D. Willis"},{"@pid":"77/6779","text":"Ivan Poupyrev"},{"@pid":"h/ScottEHudson","text":"Scott E. Hudson"},{"@pid":"36/8321","text":"Moshe Mahler"}]},"title":"SideBySide - ad-hoc multi-user interaction with handheld projectors.","venue":"UIST","pages":"431-440","year":"2011","type":"Conference and Workshop Papers","key":"conf/uist/WillisPHM11","doi":"10.1145/2047196.2047254","ee":"https://doi.org/10.1145/2047196.2047254","url":"https://dblp.org/rec/conf/uist/WillisPHM11"},
"url":"URL#3109574"
},
{
"@score":"1",
"@id":"3109575",
"info":{"authors":{"author":[{"@pid":"68/3746","text":"Raphael Wimmer"},{"@pid":"b/PatrickBaudisch","text":"Patrick Baudisch"}]},"title":"Modular and deformable touch-sensitive surfaces based on time domain reflectometry.","venue":"UIST","pages":"517-526","year":"2011","type":"Conference and Workshop Papers","key":"conf/uist/WimmerB11","doi":"10.1145/2047196.2047264","ee":"https://doi.org/10.1145/2047196.2047264","url":"https://dblp.org/rec/conf/uist/WimmerB11"},
"url":"URL#3109575"
},
{
"@score":"1",
"@id":"3109577",
"info":{"authors":{"author":[{"@pid":"17/2778","text":"Yusuke Yamamoto"},{"@pid":"14/1212","text":"Hideaki Uchiyama"},{"@pid":"03/6193","text":"Yasuaki Kakehi"}]},"title":"onNote - playing printed music scores as a musical instrument.","venue":"UIST","pages":"413-422","year":"2011","type":"Conference and Workshop Papers","key":"conf/uist/YamamotoUK11","doi":"10.1145/2047196.2047249","ee":"https://doi.org/10.1145/2047196.2047249","url":"https://dblp.org/rec/conf/uist/YamamotoUK11"},
"url":"URL#3109577"
},
{
"@score":"1",
"@id":"3109578",
"info":{"authors":{"author":[{"@pid":"05/6465","text":"Tom Yeh"},{"@pid":"76/3254","text":"Tsung-Hsiang Chang"},{"@pid":"72/6778-1","text":"Bo Xie 0001"},{"@pid":"80/6325","text":"Greg Walsh"},{"@pid":"78/9168","text":"Ivan Watkins"},{"@pid":"78/7577","text":"Krist Wongsuphasawat"},{"@pid":"12/9168","text":"Man Huang"},{"@pid":"d/LarrySDavis","text":"Larry S. Davis"},{"@pid":"b/BenBederson","text":"Benjamin B. Bederson"}]},"title":"Creating contextual help for GUIs using screenshots.","venue":"UIST","pages":"145-154","year":"2011","type":"Conference and Workshop Papers","key":"conf/uist/YehCXWWWHDB11","doi":"10.1145/2047196.2047214","ee":"https://doi.org/10.1145/2047196.2047214","url":"https://dblp.org/rec/conf/uist/YehCXWWWHDB11"},
"url":"URL#3109578"
},
{
"@score":"1",
"@id":"3109580",
"info":{"authors":{"author":[{"@pid":"05/8693","text":"Neng-Hao Yu"},{"@pid":"79/9542","text":"Sung-Sheng Tsai"},{"@pid":"30/9540","text":"I-Chun Hsiao"},{"@pid":"20/9541","text":"Dian-Je Tsai"},{"@pid":"86/10299","text":"Meng-Han Lee"},{"@pid":"83/3844","text":"Mike Y. Chen"},{"@pid":"21/1331","text":"Yi-Ping Hung"}]},"title":"Clip-on gadgets - expanding multi-touch interaction area with unpowered tactile controls.","venue":"UIST","pages":"367-372","year":"2011","type":"Conference and Workshop Papers","key":"conf/uist/YuTHTLCH11","doi":"10.1145/2047196.2047243","ee":"https://doi.org/10.1145/2047196.2047243","url":"https://dblp.org/rec/conf/uist/YuTHTLCH11"},
"url":"URL#3109580"
},
{
"@score":"1",
"@id":"3109582",
"info":{"authors":{"author":[{"@pid":"98/2000","text":"Jan Zizka"},{"@pid":"51/6280","text":"Alex Olwal"},{"@pid":"r/RameshRaskar","text":"Ramesh Raskar"}]},"title":"SpeckleSense - fast, precise, low-cost and compact motion sensing using laser speckle.","venue":"UIST","pages":"489-498","year":"2011","type":"Conference and Workshop Papers","key":"conf/uist/ZizkaOR11","doi":"10.1145/2047196.2047261","ee":"https://doi.org/10.1145/2047196.2047261","url":"https://dblp.org/rec/conf/uist/ZizkaOR11"},
"url":"URL#3109582"
},
{
"@score":"1",
"@id":"3123813",
"info":{"authors":{"author":[{"@pid":"95/4715","text":"Jeffrey S. Pierce"},{"@pid":"64/2431","text":"Maneesh Agrawala"},{"@pid":"97/4414","text":"Scott R. Klemmer"}]},"title":"Proceedings of the 24th Annual ACM Symposium on User Interface Software and Technology, Santa Barbara, CA, USA, October 16-19, 2011","venue":"UIST","publisher":"ACM","year":"2011","type":"Editorship","key":"conf/uist/2011","doi":"10.1145/2047196","ee":"https://doi.org/10.1145/2047196","url":"https://dblp.org/rec/conf/uist/2011"},
"url":"URL#3123813"
}
]
}
}
}
