{
"result":{
"query":":facetid:toc:\"db/conf/dasfaa/dasfaa93.bht\"",
"status":{
"@code":"200",
"text":"OK"
},
"time":{
"@unit":"msecs",
"text":"174.26"
},
"completions":{
"@total":"1",
"@computed":"1",
"@sent":"1",
"c":{
"@sc":"54",
"@dc":"54",
"@oc":"54",
"@id":"34729256",
"text":":facetid:toc:db/conf/dasfaa/dasfaa93.bht"
}
},
"hits":{
"@total":"54",
"@computed":"54",
"@sent":"54",
"@first":"0",
"hit":[{
"@score":"1",
"@id":"5588915",
"info":{"title":"Author Index.","venue":"DASFAA","pages":"449-450","year":"1993","type":"Conference and Workshop Papers","access":"unavailable","key":"conf/dasfaa/AI93","url":"https://dblp.org/rec/conf/dasfaa/AI93"},
"url":"URL#5588915"
},
{
"@score":"1",
"@id":"5588916",
"info":{"authors":{"author":{"@pid":"41/5076","text":"Ilsoo Ahn"}},"title":"Evaluation of a Parallel Database Machine for Caller Dependent Routing.","venue":"DASFAA","pages":"170-177","year":"1993","type":"Conference and Workshop Papers","access":"unavailable","key":"conf/dasfaa/Ahn93","url":"https://dblp.org/rec/conf/dasfaa/Ahn93"},
"url":"URL#5588916"
},
{
"@score":"1",
"@id":"5588917",
"info":{"authors":{"author":[{"@pid":"84/3469","text":"Hirofumi Amano"},{"@pid":"k/YahikoKambayashi","text":"Yahiko Kambayashi"}]},"title":"Relational Query Formulation by Pseudonatural Language Text Manipulation.","venue":"DASFAA","pages":"11-18","year":"1993","type":"Conference and Workshop Papers","access":"unavailable","key":"conf/dasfaa/AmanoK93","url":"https://dblp.org/rec/conf/dasfaa/AmanoK93"},
"url":"URL#5588917"
},
{
"@score":"1",
"@id":"5588918",
"info":{"authors":{"author":[{"@pid":"b/GabrielABaum","text":"Gabriel Baum"},{"@pid":"g/SilviaEGordillo","text":"Silvia E. Gordillo"},{"@pid":"p/ClaudiaPons","text":"Claudia Pons"},{"@pid":"65/6238","text":"Clara Smith"},{"@pid":"12/805","text":"Carlos A. Tau"}]},"title":"Conceptual Layers in an Object Oriented Database. An Unified Model.","venue":"DASFAA","pages":"141-147","year":"1993","type":"Conference and Workshop Papers","access":"unavailable","key":"conf/dasfaa/BaumGPST93","url":"https://dblp.org/rec/conf/dasfaa/BaumGPST93"},
"url":"URL#5588918"
},
{
"@score":"1",
"@id":"5588919",
"info":{"authors":{"author":[{"@pid":"08/2052","text":"Jean-Pierre Cheiney"},{"@pid":"k/JerryKiernan","text":"Gerald Kiernan"},{"@pid":"78/5517","text":"Christophe de Maindreville"}]},"title":"A Database Rule Language Compiler Supporting Parallelism.","venue":"DASFAA","pages":"279-286","year":"1993","type":"Conference and Workshop Papers","access":"unavailable","key":"conf/dasfaa/CheineyKM93","url":"https://dblp.org/rec/conf/dasfaa/CheineyKM93"},
"url":"URL#5588919"
},
{
"@score":"1",
"@id":"5588920",
"info":{"authors":{"author":[{"@pid":"32/6638","text":"Hanxiong Chen"},{"@pid":"y/JXuYu","text":"Jeffrey Xu Yu"},{"@pid":"79/3563","text":"Kazunori Yamaguchi"},{"@pid":"k/HiroyukiKitagawa","text":"Hiroyuki Kitagawa"},{"@pid":"79/1829","text":"Nobuo Ohbo"},{"@pid":"87/2326","text":"Yuzuru Fujiwara"}]},"title":"LRU-S - A New Buffer Allocation Approach for OODBMS.","venue":"DASFAA","pages":"73-80","year":"1993","type":"Conference and Workshop Papers","access":"unavailable","key":"conf/dasfaa/ChenYYKOF93","url":"https://dblp.org/rec/conf/dasfaa/ChenYYKOF93"},
"url":"URL#5588920"
},
{
"@score":"1",
"@id":"5588921",
"info":{"authors":{"author":[{"@pid":"33/3590","text":"TaeNam Cho"},{"@pid":"64/4387","text":"Kyung-Chang Kim"}]},"title":"Design of Historical Databases Using the 3-D Relational Data Model.","venue":"DASFAA","pages":"297-305","year":"1993","type":"Conference and Workshop Papers","access":"unavailable","key":"conf/dasfaa/ChoK93","url":"https://dblp.org/rec/conf/dasfaa/ChoK93"},
"url":"URL#5588921"
},
{
"@score":"1",
"@id":"5588922",
"info":{"authors":{"author":[{"@pid":"63/4272","text":"Dong-Hoon Choi"},{"@pid":"h/LawrenceJHenschen","text":"Lawrence J. Henschen"}]},"title":"On Exclusive Disjunctions in Deductive Database.","venue":"DASFAA","pages":"353-359","year":"1993","type":"Conference and Workshop Papers","access":"unavailable","key":"conf/dasfaa/ChoiH93","url":"https://dblp.org/rec/conf/dasfaa/ChoiH93"},
"url":"URL#5588922"
},
{
"@score":"1",
"@id":"5588923",
"info":{"authors":{"author":{"@pid":"c/SoonMyoungChung","text":"Soon Myoung Chung"}},"title":"Enhanced Tree Quorum Algorithm for Replicated Distributed Databases.","venue":"DASFAA","pages":"83-89","year":"1993","type":"Conference and Workshop Papers","access":"unavailable","key":"conf/dasfaa/Chung93","url":"https://dblp.org/rec/conf/dasfaa/Chung93"},
"url":"URL#5588923"
},
{
"@score":"1",
"@id":"5588924",
"info":{"authors":{"author":[{"@pid":"c/SoonMyoungChung","text":"Soon Myoung Chung"},{"@pid":"35/5356","text":"Jaerheen Yang"}]},"title":"Distributive Join Algorithm for Cube-Connected Multiprocessors.","venue":"DASFAA","pages":"253-260","year":"1993","type":"Conference and Workshop Papers","access":"unavailable","key":"conf/dasfaa/ChungY93","url":"https://dblp.org/rec/conf/dasfaa/ChungY93"},
"url":"URL#5588924"
},
{
"@score":"1",
"@id":"5588925",
"info":{"authors":{"author":[{"@pid":"73/111","text":"Toncan Duong"},{"@pid":"71/1983","text":"John Hiller"},{"@pid":"n/AnneHHNgu","text":"Anne H. H. Ngu"}]},"title":"Information Integration through Contract.","venue":"DASFAA","pages":"107-114","year":"1993","type":"Conference and Workshop Papers","access":"unavailable","key":"conf/dasfaa/DuongHN93","url":"https://dblp.org/rec/conf/dasfaa/DuongHN93"},
"url":"URL#5588925"
},
{
"@score":"1",
"@id":"5588926",
"info":{"title":"Title, Preface, PC Chairperson&apos;s Message, OC Chairperson&apos;s Message, Organization, Referees.","venue":"DASFAA","year":"1993","type":"Conference and Workshop Papers","access":"unavailable","key":"conf/dasfaa/FM93","url":"https://dblp.org/rec/conf/dasfaa/FM93"},
"url":"URL#5588926"
},
{
"@score":"1",
"@id":"5588927",
"info":{"authors":{"author":[{"@pid":"88/3255","text":"Kazutaka Furuse"},{"@pid":"79/3563","text":"Kazunori Yamaguchi"},{"@pid":"k/HiroyukiKitagawa","text":"Hiroyuki Kitagawa"},{"@pid":"79/1829","text":"Nobuo Ohbo"}]},"title":"Abstract Indexing Mechanism of the Extensible DBMS Modus.","venue":"DASFAA","pages":"189-196","year":"1993","type":"Conference and Workshop Papers","access":"unavailable","key":"conf/dasfaa/FuruseYKO93","url":"https://dblp.org/rec/conf/dasfaa/FuruseYKO93"},
"url":"URL#5588927"
},
{
"@score":"1",
"@id":"5588928",
"info":{"authors":{"author":[{"@pid":"99/3539","text":"Susumu Goto"},{"@pid":"59/1201","text":"Norihiro Sakamoto"},{"@pid":"54/2114","text":"Toshihisa Takagi"}]},"title":"Object-Oriented Database with Rule-Based Query Interface for Genomic Computation.","venue":"DASFAA","pages":"65-72","year":"1993","type":"Conference and Workshop Papers","access":"unavailable","key":"conf/dasfaa/GotoST93","url":"https://dblp.org/rec/conf/dasfaa/GotoST93"},
"url":"URL#5588928"
},
{
"@score":"1",
"@id":"5588929",
"info":{"authors":{"author":[{"@pid":"72/784","text":"Jonas M. de Graaff"},{"@pid":"53/2970","text":"René J. Veldwijk"},{"@pid":"20/5490","text":"Martin Boogaard"}]},"title":"Logical Data Independence Via Views - A Misapprehension?","venue":"DASFAA","pages":"313-323","year":"1993","type":"Conference and Workshop Papers","access":"unavailable","key":"conf/dasfaa/GraaffVB93","url":"https://dblp.org/rec/conf/dasfaa/GraaffVB93"},
"url":"URL#5588929"
},
{
"@score":"1",
"@id":"5588930",
"info":{"authors":{"author":{"@pid":"g/SergioGreco","text":"Sergio Greco"}},"title":"Optimization of Chain Queries.","venue":"DASFAA","pages":"261-268","year":"1993","type":"Conference and Workshop Papers","access":"unavailable","key":"conf/dasfaa/Greco93","url":"https://dblp.org/rec/conf/dasfaa/Greco93"},
"url":"URL#5588930"
},
{
"@score":"1",
"@id":"5588931",
"info":{"authors":{"author":[{"@pid":"03/6073","text":"Jorng-Tzong Horng"},{"@pid":"29/6120","text":"Gwo-Dong Chen"},{"@pid":"16/64","text":"Baw-Jhiune Liu"}]},"title":"Query Processing Techniques in the Team-Oriented Database Query Language.","venue":"DASFAA","pages":"245-252","year":"1993","type":"Conference and Workshop Papers","access":"unavailable","key":"conf/dasfaa/HorngCL93","url":"https://dblp.org/rec/conf/dasfaa/HorngCL93"},
"url":"URL#5588931"
},
{
"@score":"1",
"@id":"5588932",
"info":{"authors":{"author":[{"@pid":"51/1466","text":"Kitae Hwang"},{"@pid":"08/4789","text":"Heonshik Shin"}]},"title":"New Disk Scheduling Algorithms for Reduced Rotational Latency.","venue":"DASFAA","pages":"395-402","year":"1993","type":"Conference and Workshop Papers","access":"unavailable","key":"conf/dasfaa/HwangS93","url":"https://dblp.org/rec/conf/dasfaa/HwangS93"},
"url":"URL#5588932"
},
{
"@score":"1",
"@id":"5588933",
"info":{"authors":{"author":[{"@pid":"71/1470","text":"Minoru Ito"},{"@pid":"61/3277","text":"Michio Nakanishi"}]},"title":"On Deriving Specialization Constraints over Complex Objects.","venue":"DASFAA","pages":"335-342","year":"1993","type":"Conference and Workshop Papers","access":"unavailable","key":"conf/dasfaa/ItoN93","url":"https://dblp.org/rec/conf/dasfaa/ItoN93"},
"url":"URL#5588933"
},
{
"@score":"1",
"@id":"5588934",
"info":{"authors":{"author":[{"@pid":"k/KunihikoKaneko","text":"Kunihiko Kaneko"},{"@pid":"85/2404","text":"Susumu Kuroki"},{"@pid":"29/5712","text":"Akifumi Makinouchi"}]},"title":"Towards Dynamics Animation on Object-Oriented Animation Database System &quot;MOVE&quot;.","venue":"DASFAA","pages":"3-10","year":"1993","type":"Conference and Workshop Papers","access":"unavailable","key":"conf/dasfaa/KanekoKM93","url":"https://dblp.org/rec/conf/dasfaa/KanekoKM93"},
"url":"URL#5588934"
},
{
"@score":"1",
"@id":"5588935",
"info":{"authors":{"author":[{"@pid":"38/898","text":"Yang Hee Kim"},{"@pid":"k/HyoungJooKim","text":"Hyoung-Joo Kim"}]},"title":"Applying Intensional Query Processing Techniques to Object-Oriented Database Systems.","venue":"DASFAA","pages":"405-412","year":"1993","type":"Conference and Workshop Papers","access":"unavailable","key":"conf/dasfaa/KimK93","url":"https://dblp.org/rec/conf/dasfaa/KimK93"},
"url":"URL#5588935"
},
{
"@score":"1",
"@id":"5588936",
"info":{"authors":{"author":[{"@pid":"31/6517","text":"Junguk L. Kim"},{"@pid":"11/5020","text":"Taesoon Park"},{"@pid":"188/7871","text":"Prabaharan I. Swarnam"},{"@pid":"07/3704","text":"M.-J. Kim"}]},"title":"A Protocol for Consistent Checkpointing Recovery for Time-Critical Distributed Database Systems.","venue":"DASFAA","pages":"227-234","year":"1993","type":"Conference and Workshop Papers","access":"unavailable","key":"conf/dasfaa/KimPSK93","url":"https://dblp.org/rec/conf/dasfaa/KimPSK93"},
"url":"URL#5588936"
},
{
"@score":"1",
"@id":"5588937",
"info":{"authors":{"author":{"@pid":"26/6562","text":"John K. Lee"}},"title":"B-Tree Concurrency Control Algorithm for Nested Transaction Systems.","venue":"DASFAA","pages":"205-215","year":"1993","type":"Conference and Workshop Papers","access":"unavailable","key":"conf/dasfaa/Lee93","url":"https://dblp.org/rec/conf/dasfaa/Lee93"},
"url":"URL#5588937"
},
{
"@score":"1",
"@id":"5588938",
"info":{"authors":{"author":[{"@pid":"56/4945","text":"Joon Ho Lee"},{"@pid":"91/1909","text":"Won Yong Kim"},{"@pid":"k/Myoung-HoKim","text":"Myoung-Ho Kim"},{"@pid":"l/YoonJoonLee","text":"Yoon-Joon Lee"}]},"title":"Enhancing the Fuzzy Set Model with Positively Compensatory Operators.","venue":"DASFAA","pages":"368-375","year":"1993","type":"Conference and Workshop Papers","access":"unavailable","key":"conf/dasfaa/LeeKKL93","url":"https://dblp.org/rec/conf/dasfaa/LeeKKL93"},
"url":"URL#5588938"
},
{
"@score":"1",
"@id":"5588939",
"info":{"authors":{"author":[{"@pid":"43/1124","text":"Doheon Lee"},{"@pid":"k/Myoung-HoKim","text":"Myoung-Ho Kim"},{"@pid":"53/749","text":"Hyung Lee-Kwang"},{"@pid":"l/YoonJoonLee","text":"Yoon-Joon Lee"}]},"title":"A Fuzzification of the Relational Data Model.","venue":"DASFAA","pages":"360-367","year":"1993","type":"Conference and Workshop Papers","access":"unavailable","key":"conf/dasfaa/LeeKLL93","url":"https://dblp.org/rec/conf/dasfaa/LeeKLL93"},
"url":"URL#5588939"
},
{
"@score":"1",
"@id":"5588940",
"info":{"authors":{"author":[{"@pid":"01/4794","text":"Juhnyoung Lee"},{"@pid":"s/SangHyukSon","text":"Sang Hyuk Son"}]},"title":"An Optimistic Concurrency Control Protocol for Real-Time Database Systems.","venue":"DASFAA","pages":"387-394","year":"1993","type":"Conference and Workshop Papers","access":"unavailable","key":"conf/dasfaa/LeeS93","url":"https://dblp.org/rec/conf/dasfaa/LeeS93"},
"url":"URL#5588940"
},
{
"@score":"1",
"@id":"5588941",
"info":{"authors":{"author":[{"@pid":"96/5639","text":"Chiang Lee"},{"@pid":"88/5889","text":"Cheng-Lun Tsai"}]},"title":"Strategies for Selection from Heterogeneous Relations.","venue":"DASFAA","pages":"97-104","year":"1993","type":"Conference and Workshop Papers","access":"unavailable","key":"conf/dasfaa/LeeT93","url":"https://dblp.org/rec/conf/dasfaa/LeeT93"},
"url":"URL#5588941"
},
{
"@score":"1",
"@id":"5588942",
"info":{"authors":{"author":[{"@pid":"98/6308","text":"J. Liang"},{"@pid":"c/ChinChenChang","text":"Chin-Chen Chang 0001"}]},"title":"Similarity Retrieval on Pictorial Databases Based upon Module Operation.","venue":"DASFAA","pages":"19-26","year":"1993","type":"Conference and Workshop Papers","access":"unavailable","key":"conf/dasfaa/LiangC93","url":"https://dblp.org/rec/conf/dasfaa/LiangC93"},
"url":"URL#5588942"
},
{
"@score":"1",
"@id":"5588943",
"info":{"authors":{"author":[{"@pid":"l/TokWangLing","text":"Tok Wang Ling"},{"@pid":"04/1907","text":"Sin Yeung Lee"}]},"title":"Improving Integrity Checking for Exists-Constraints.","venue":"DASFAA","pages":"343-350","year":"1993","type":"Conference and Workshop Papers","access":"unavailable","key":"conf/dasfaa/LingL93","url":"https://dblp.org/rec/conf/dasfaa/LingL93"},
"url":"URL#5588943"
},
{
"@score":"1",
"@id":"5588944",
"info":{"authors":{"author":[{"@pid":"l/TokWangLing","text":"Tok Wang Ling"},{"@pid":"46/821","text":"Pit Koon Teo"},{"@pid":"y/LingLingYan","text":"Ling-Ling Yan"}]},"title":"Generating Object-Oriented Views from an ER-Based Conceptual Schema.","venue":"DASFAA","pages":"148-155","year":"1993","type":"Conference and Workshop Papers","access":"unavailable","key":"conf/dasfaa/LingTY93","url":"https://dblp.org/rec/conf/dasfaa/LingTY93"},
"url":"URL#5588944"
},
{
"@score":"1",
"@id":"5588945",
"info":{"authors":{"author":[{"@pid":"18/2691","text":"D. Maino"},{"@pid":"09/5699","text":"F. Mercalli"},{"@pid":"98/7021","text":"R. Negrini"}]},"title":"A Multimedia Database for an Advanced Teleshopping Application.","venue":"DASFAA","pages":"442-448","year":"1993","type":"Conference and Workshop Papers","access":"unavailable","key":"conf/dasfaa/MainoMN93","url":"https://dblp.org/rec/conf/dasfaa/MainoMN93"},
"url":"URL#5588945"
},
{
"@score":"1",
"@id":"5588946",
"info":{"authors":{"author":{"@pid":"03/2361","text":"Subhasish Mazumdar"}},"title":"Optimizing Distributed Integrity Constraints.","venue":"DASFAA","pages":"327-334","year":"1993","type":"Conference and Workshop Papers","access":"unavailable","key":"conf/dasfaa/Mazumdar93","url":"https://dblp.org/rec/conf/dasfaa/Mazumdar93"},
"url":"URL#5588946"
},
{
"@score":"1",
"@id":"5588947",
"info":{"authors":{"author":[{"@pid":"m/SharadMehrotra","text":"Sharad Mehrotra"},{"@pid":"r/RajeevRastogi","text":"Rajeev Rastogi"},{"@pid":"b/YuriBreitbart","text":"Yuri Breitbart"},{"@pid":"k/HenryFKorth","text":"Henry F. Korth"},{"@pid":"s/AbrahamSilberschatz","text":"Abraham Silberschatz"}]},"title":"Efficient Global Transaction Management in Multidatabase Systems.","venue":"DASFAA","pages":"29-36","year":"1993","type":"Conference and Workshop Papers","access":"unavailable","key":"conf/dasfaa/MehrotraRBKS93","url":"https://dblp.org/rec/conf/dasfaa/MehrotraRBKS93"},
"url":"URL#5588947"
},
{
"@score":"1",
"@id":"5588948",
"info":{"authors":{"author":{"@pid":"57/4535","text":"Thomas A. Mück"}},"title":"The DiNG - A Parallel Multiattribute File System for Deductive Database Machines.","venue":"DASFAA","pages":"115-122","year":"1993","type":"Conference and Workshop Papers","access":"unavailable","key":"conf/dasfaa/Muck93","url":"https://dblp.org/rec/conf/dasfaa/Muck93"},
"url":"URL#5588948"
},
{
"@score":"1",
"@id":"5588949",
"info":{"authors":{"author":[{"@pid":"n/AnneHHNgu","text":"Anne H. H. Ngu"},{"@pid":"w/LimsoonWong","text":"Limsoon Wong"}]},"title":"PINOL - A Persistent Inferential Object Oriented Language for Databases.","venue":"DASFAA","pages":"57-64","year":"1993","type":"Conference and Workshop Papers","access":"unavailable","key":"conf/dasfaa/NguW93","url":"https://dblp.org/rec/conf/dasfaa/NguW93"},
"url":"URL#5588949"
},
{
"@score":"1",
"@id":"5588950",
"info":{"authors":{"author":[{"@pid":"n/AnneHHNgu","text":"Anne H. H. Ngu"},{"@pid":"y/LingLingYan","text":"Ling-Ling Yan"},{"@pid":"w/LimsoonWong","text":"Limsoon Wong"}]},"title":"Heterogeneous Query Optimization Using Maximal Sub-Queries.","venue":"DASFAA","pages":"413-420","year":"1993","type":"Conference and Workshop Papers","access":"unavailable","key":"conf/dasfaa/NguYW93","url":"https://dblp.org/rec/conf/dasfaa/NguYW93"},
"url":"URL#5588950"
},
{
"@score":"1",
"@id":"5588951",
"info":{"authors":{"author":[{"@pid":"84/4198","text":"Yasushi Ogawa"},{"@pid":"90/6086","text":"Ayako Bessho"},{"@pid":"33/8305","text":"Masajiro Iwasaki"},{"@pid":"273/4580","text":"Mina Nishimura"},{"@pid":"99/1667","text":"Masako Hirose"}]},"title":"A New Indexing and Text Ranking Method for Japanese Text Databases Using Simple-Word Compounds as Keywords.","venue":"DASFAA","pages":"197-204","year":"1993","type":"Conference and Workshop Papers","access":"unavailable","key":"conf/dasfaa/OgawaBINH93","url":"https://dblp.org/rec/conf/dasfaa/OgawaBINH93"},
"url":"URL#5588951"
},
{
"@score":"1",
"@id":"5588952",
"info":{"authors":{"author":[{"@pid":"10/180","text":"Sang Hun Oh"},{"@pid":"l/YoonJoonLee","text":"Yoon-Joon Lee"},{"@pid":"k/Myoung-HoKim","text":"Myoung-Ho Kim"}]},"title":"Qualitative Behavior Modeling of Information Processing Components.","venue":"DASFAA","pages":"435-441","year":"1993","type":"Conference and Workshop Papers","access":"unavailable","key":"conf/dasfaa/OhLK93","url":"https://dblp.org/rec/conf/dasfaa/OhLK93"},
"url":"URL#5588952"
},
{
"@score":"1",
"@id":"5588953",
"info":{"authors":{"author":[{"@pid":"43/4999","text":"Minyoung Ra"},{"@pid":"93/6183","text":"Y.-S. Park"}]},"title":"Data Fragmentation and Allocation for PC-Based Distributed Database Design.","venue":"DASFAA","pages":"90-96","year":"1993","type":"Conference and Workshop Papers","access":"unavailable","key":"conf/dasfaa/RaP93","url":"https://dblp.org/rec/conf/dasfaa/RaP93"},
"url":"URL#5588953"
},
{
"@score":"1",
"@id":"5588954",
"info":{"authors":{"author":[{"@pid":"11/5953","text":"Satyendra P. Rana"},{"@pid":"f/FarshadFotouhi","text":"Farshad Fotouhi"}]},"title":"Efficient Processing of Time-Joins in Temporal Data Bases.","venue":"DASFAA","pages":"427-432","year":"1993","type":"Conference and Workshop Papers","access":"unavailable","key":"conf/dasfaa/RanaF93","url":"https://dblp.org/rec/conf/dasfaa/RanaF93"},
"url":"URL#5588954"
},
{
"@score":"1",
"@id":"5588955",
"info":{"authors":{"author":[{"@pid":"55/2755","text":"Abad A. Shah"},{"@pid":"f/FarshadFotouhi","text":"Farshad Fotouhi"},{"@pid":"g/WilliamIGrosky","text":"William I. Grosky"},{"@pid":"11/5953","text":"Satyendra P. Rana"},{"@pid":"34/1427","text":"A. Vashishta"}]},"title":"Offstage Objects and their Renovations in the Temporal Object System TOS.","venue":"DASFAA","pages":"306-312","year":"1993","type":"Conference and Workshop Papers","access":"unavailable","key":"conf/dasfaa/ShahFGRV93","url":"https://dblp.org/rec/conf/dasfaa/ShahFGRV93"},
"url":"URL#5588955"
},
{
"@score":"1",
"@id":"5588956",
"info":{"authors":{"author":[{"@pid":"s/SangHyukSon","text":"Sang Hyuk Son"},{"@pid":"71/3080","text":"Spiros Kouloumbis"}]},"title":"A Token-Based Synchronization Scheme Using Epsilon-Serializability and Its Performance for Real-Time Distributed Database Systems.","venue":"DASFAA","pages":"235-242","year":"1993","type":"Conference and Workshop Papers","access":"unavailable","key":"conf/dasfaa/SonK93","url":"https://dblp.org/rec/conf/dasfaa/SonK93"},
"url":"URL#5588956"
},
{
"@score":"1",
"@id":"5588957",
"info":{"authors":{"author":[{"@pid":"s/SangHyukSon","text":"Sang Hyuk Son"},{"@pid":"10/2382","text":"Seok Park"}]},"title":"Scheduling and Concurrency Control for Real-Time Database Systems.","venue":"DASFAA","pages":"219-226","year":"1993","type":"Conference and Workshop Papers","access":"unavailable","key":"conf/dasfaa/SonP93","url":"https://dblp.org/rec/conf/dasfaa/SonP93"},
"url":"URL#5588957"
},
{
"@score":"1",
"@id":"5588958",
"info":{"authors":{"author":[{"@pid":"s/IlYeolSong","text":"Il-Yeol Song"},{"@pid":"51/1239","text":"Heather M. Godsey"}]},"title":"A Knowledge Based System Converting ER Model into an Object-Oriented Database Schema.","venue":"DASFAA","pages":"287-294","year":"1993","type":"Conference and Workshop Papers","access":"unavailable","key":"conf/dasfaa/SongG93","url":"https://dblp.org/rec/conf/dasfaa/SongG93"},
"url":"URL#5588958"
},
{
"@score":"1",
"@id":"5588959",
"info":{"authors":{"author":[{"@pid":"s/StanleyYWSu","text":"Stanley Y. W. Su"},{"@pid":"85/1315","text":"Soon J. Hyun"},{"@pid":"79/3334","text":"Rahul B. Patel"}]},"title":"A Parallel Pattern Search Algorithm for Processing Object-Oriented Databases in a Cellular Array Architecture.","venue":"DASFAA","pages":"159-169","year":"1993","type":"Conference and Workshop Papers","access":"unavailable","key":"conf/dasfaa/SuHP93","url":"https://dblp.org/rec/conf/dasfaa/SuHP93"},
"url":"URL#5588959"
},
{
"@score":"1",
"@id":"5588960",
"info":{"authors":{"author":{"@pid":"95/4455","text":"Junichi Takahashi"}},"title":"Temporal Query Processing for Scene Retrieval in Motion Image Databases.","venue":"DASFAA","pages":"421-426","year":"1993","type":"Conference and Workshop Papers","access":"unavailable","key":"conf/dasfaa/Takahashi93","url":"https://dblp.org/rec/conf/dasfaa/Takahashi93"},
"url":"URL#5588960"
},
{
"@score":"1",
"@id":"5588961",
"info":{"authors":{"author":[{"@pid":"99/4054","text":"Hiroki Takakura"},{"@pid":"k/YahikoKambayashi","text":"Yahiko Kambayashi"}]},"title":"A Design of a Transparent Backup System Using a Main Memory Database.","venue":"DASFAA","pages":"178-185","year":"1993","type":"Conference and Workshop Papers","access":"unavailable","key":"conf/dasfaa/TakakuraK93","url":"https://dblp.org/rec/conf/dasfaa/TakakuraK93"},
"url":"URL#5588961"
},
{
"@score":"1",
"@id":"5588962",
"info":{"authors":{"author":[{"@pid":"30/204","text":"Markus Tresch"},{"@pid":"s/MarcHScholl","text":"Marc H. Scholl"}]},"title":"Schema Transformation Processors for Federated Objectbases.","venue":"DASFAA","pages":"37-46","year":"1993","type":"Conference and Workshop Papers","access":"unavailable","key":"conf/dasfaa/TreschS93","url":"https://dblp.org/rec/conf/dasfaa/TreschS93"},
"url":"URL#5588962"
},
{
"@score":"1",
"@id":"5588963",
"info":{"authors":{"author":[{"@pid":"y/JianYang1","text":"Jian Yang 0001"},{"@pid":"p/MPPapazoglou","text":"Mike P. Papazoglou"}]},"title":"Determining Schema Interdependencies in Object-Oriented Multidatabase Systems.","venue":"DASFAA","pages":"47-54","year":"1993","type":"Conference and Workshop Papers","access":"unavailable","key":"conf/dasfaa/YangP93","url":"https://dblp.org/rec/conf/dasfaa/YangP93"},
"url":"URL#5588963"
},
{
"@score":"1",
"@id":"5588964",
"info":{"authors":{"author":{"@pid":"86/247","text":"Jing P. Yoon"}},"title":"Database Updates Using Active Rules - A Unified Approach for Consistency Maintenance.","venue":"DASFAA","pages":"271-278","year":"1993","type":"Conference and Workshop Papers","access":"unavailable","key":"conf/dasfaa/Yoon93","url":"https://dblp.org/rec/conf/dasfaa/Yoon93"},
"url":"URL#5588964"
},
{
"@score":"1",
"@id":"5588965",
"info":{"authors":{"author":[{"@pid":"89/1675","text":"Hyunyoon Yun"},{"@pid":"52/256","text":"Buhyun Hwang"}]},"title":"A Pessimistic Concurrency Control Algorithm in Multidatabase Systems.","venue":"DASFAA","pages":"379-386","year":"1993","type":"Conference and Workshop Papers","access":"unavailable","key":"conf/dasfaa/YunH93","url":"https://dblp.org/rec/conf/dasfaa/YunH93"},
"url":"URL#5588965"
},
{
"@score":"1",
"@id":"5588966",
"info":{"authors":{"author":[{"@pid":"27/6649","text":"Huibin Zhao"},{"@pid":"b/ABiliris","text":"Alexandros Biliris"}]},"title":"An Object-Centered Data Model for Engineering Design Databases.","venue":"DASFAA","pages":"133-140","year":"1993","type":"Conference and Workshop Papers","access":"unavailable","key":"conf/dasfaa/ZhaoB93","url":"https://dblp.org/rec/conf/dasfaa/ZhaoB93"},
"url":"URL#5588966"
},
{
"@score":"1",
"@id":"5588967",
"info":{"authors":{"author":[{"@pid":"19/6643","text":"Cuie Zhao"},{"@pid":"31/6532","text":"Ging Yang Choo"},{"@pid":"48/6546","text":"Kia Chek Phua"},{"@pid":"05/1430","text":"Robin C. G. Seow"}]},"title":"Database User Interface Design Editor.","venue":"DASFAA","pages":"123-130","year":"1993","type":"Conference and Workshop Papers","access":"unavailable","key":"conf/dasfaa/ZhaoCPS93","url":"https://dblp.org/rec/conf/dasfaa/ZhaoCPS93"},
"url":"URL#5588967"
},
{
"@score":"1",
"@id":"5606201",
"info":{"authors":{"author":[{"@pid":"43/5366","text":"Song C. Moon"},{"@pid":"93/2315","text":"Hideto Ikeda"}]},"title":"Proceedings of the 3rd International Conference on Database Systems for Advanced Applications (DASFAA), Daejeon, Korea, April 6-8, 1993","venue":"Advanced Database Research and Development Series","volume":"4","publisher":"World Scientific","year":"1993","type":"Editorship","access":"unavailable","key":"conf/dasfaa/93","url":"https://dblp.org/rec/conf/dasfaa/93"},
"url":"URL#5606201"
}
]
}
}
}
