{
"result":{
"query":":facetid:toc:db\"/\"conf\"/\"focs\"/\"focs96\".\"bht",
"status":{
"@code":"200",
"text":"OK"
},
"time":{
"@unit":"msecs",
"text":"106.18"
},
"completions":{
"@total":"1",
"@computed":"1",
"@sent":"1",
"c":{
"@sc":"66",
"@dc":"66",
"@oc":"66",
"@id":"17573975",
"text":":facetid:toc:db/conf/focs/focs96.bht"
}
},
"hits":{
"@total":"66",
"@computed":"66",
"@sent":"66",
"@first":"0",
"hit":[{
"@score":"1",
"@id":"5003053",
"info":{"authors":{"author":{"@pid":"a/MicahAdler","text":"Micah Adler"}},"title":"New Coding Techniques for Improved Bandwidth Utilization.","venue":"FOCS","pages":"173-182","year":"1996","type":"Conference and Workshop Papers","key":"conf/focs/Adler96","doi":"10.1109/SFCS.1996.548476","ee":"https://doi.org/10.1109/SFCS.1996.548476","url":"https://dblp.org/rec/conf/focs/Adler96"},
"url":"URL#5003053"
},
{
"@score":"1",
"@id":"5003054",
"info":{"authors":{"author":[{"@pid":"a/PankajKAgarwal","text":"Pankaj K. Agarwal"},{"@pid":"59/5948","text":"Edward F. Grove"},{"@pid":"76/2280","text":"T. M. Murali 0001"},{"@pid":"v/JeffreyScottVitter","text":"Jeffrey Scott Vitter"}]},"title":"Binary Search Partitions for Fat Rectangles.","venue":"FOCS","pages":"482-491","year":"1996","type":"Conference and Workshop Papers","key":"conf/focs/AgarwalGMV96","doi":"10.1109/SFCS.1996.548507","ee":"https://doi.org/10.1109/SFCS.1996.548507","url":"https://dblp.org/rec/conf/focs/AgarwalGMV96"},
"url":"URL#5003054"
},
{
"@score":"1",
"@id":"5003055",
"info":{"authors":{"author":[{"@pid":"a/ManindraAgrawal","text":"Manindra Agrawal"},{"@pid":"t/ThomasThierauf","text":"Thomas Thierauf"}]},"title":"The Boolean Isomorphism Problem.","venue":"FOCS","pages":"422-430","year":"1996","type":"Conference and Workshop Papers","key":"conf/focs/AgrawalT96","doi":"10.1109/SFCS.1996.548501","ee":"https://doi.org/10.1109/SFCS.1996.548501","url":"https://dblp.org/rec/conf/focs/AgrawalT96"},
"url":"URL#5003055"
},
{
"@score":"1",
"@id":"5003056",
"info":{"authors":{"author":[{"@pid":"42/5385","text":"Dorit Aharonov"},{"@pid":"22/6416","text":"Michael Ben-Or"}]},"title":"Polynomial Simulations of Decohered Quantum Computers.","venue":"FOCS","pages":"46-55","year":"1996","type":"Conference and Workshop Papers","key":"conf/focs/AharonovB96","doi":"10.1109/SFCS.1996.548463","ee":"https://doi.org/10.1109/SFCS.1996.548463","url":"https://dblp.org/rec/conf/focs/AharonovB96"},
"url":"URL#5003056"
},
{
"@score":"1",
"@id":"5003057",
"info":{"authors":{"author":[{"@pid":"a/NAlon","text":"Noga Alon"},{"@pid":"08/2844","text":"Dmitry N. Kozlov"},{"@pid":"v/VanHVu","text":"Van H. Vu"}]},"title":"The Geometry of Coin-Weighing Problems.","venue":"FOCS","pages":"524-532","year":"1996","type":"Conference and Workshop Papers","key":"conf/focs/AlonKV96","doi":"10.1109/SFCS.1996.548511","ee":"https://doi.org/10.1109/SFCS.1996.548511","url":"https://dblp.org/rec/conf/focs/AlonKV96"},
"url":"URL#5003057"
},
{
"@score":"1",
"@id":"5003058",
"info":{"authors":{"author":[{"@pid":"81/1012","text":"Kazuyuki Amano"},{"@pid":"31/1495","text":"Akira Maruoka"}]},"title":"Potential of the Approximation Method (extended abstract).","venue":"FOCS","pages":"431-440","year":"1996","type":"Conference and Workshop Papers","key":"conf/focs/AmanoM96","doi":"10.1109/SFCS.1996.548502","ee":"https://doi.org/10.1109/SFCS.1996.548502","url":"https://dblp.org/rec/conf/focs/AmanoM96"},
"url":"URL#5003058"
},
{
"@score":"1",
"@id":"5003059",
"info":{"authors":{"author":{"@pid":"93/6067","text":"Richard J. Anderson"}},"title":"Tree Data Structures for N-Body Simulation.","venue":"FOCS","pages":"224-233","year":"1996","type":"Conference and Workshop Papers","key":"conf/focs/Anderson96","doi":"10.1109/SFCS.1996.548481","ee":"https://doi.org/10.1109/SFCS.1996.548481","url":"https://dblp.org/rec/conf/focs/Anderson96"},
"url":"URL#5003059"
},
{
"@score":"1",
"@id":"5003060",
"info":{"authors":{"author":{"@pid":"a/AAndersson","text":"Arne Andersson"}},"title":"Faster Deterministic Sorting and Searching in Linear Space.","venue":"FOCS","pages":"135-141","year":"1996","type":"Conference and Workshop Papers","key":"conf/focs/Andersson96","doi":"10.1109/SFCS.1996.548472","ee":"https://doi.org/10.1109/SFCS.1996.548472","url":"https://dblp.org/rec/conf/focs/Andersson96"},
"url":"URL#5003060"
},
{
"@score":"1",
"@id":"5003061",
"info":{"authors":{"author":[{"@pid":"a/AAndersson","text":"Arne Andersson"},{"@pid":"m/PBMiltersen","text":"Peter Bro Miltersen"},{"@pid":"19/2253","text":"Søren Riis"},{"@pid":"t/MikkelThorup","text":"Mikkel Thorup"}]},"title":"Static Dictionaries on AC0 RAMs - Query Time Theta(sqrt(log n/log log n)) is Necessary and Sufficient.","venue":"FOCS","pages":"441-450","year":"1996","type":"Conference and Workshop Papers","key":"conf/focs/AnderssonMRT96","doi":"10.1109/SFCS.1996.548503","ee":"https://doi.org/10.1109/SFCS.1996.548503","url":"https://dblp.org/rec/conf/focs/AnderssonMRT96"},
"url":"URL#5003061"
},
{
"@score":"1",
"@id":"5003062",
"info":{"authors":{"author":[{"@pid":"a/MatthewAndrews","text":"Matthew Andrews"},{"@pid":"a/BaruchAwerbuch","text":"Baruch Awerbuch"},{"@pid":"f/AntonioFernandezAnta","text":"Antonio Fernández 0001"},{"@pid":"k/JonMKleinberg","text":"Jon M. Kleinberg"},{"@pid":"l/FrankThomsonLeighton","text":"Frank Thomson Leighton"},{"@pid":"16/5205","text":"Zhiyong Liu"}]},"title":"Universal Stability Results for Greedy Contention-Resolution Protocols.","venue":"FOCS","pages":"380-389","year":"1996","type":"Conference and Workshop Papers","key":"conf/focs/AndrewsAFKLL96","doi":"10.1109/SFCS.1996.548497","ee":"https://doi.org/10.1109/SFCS.1996.548497","url":"https://dblp.org/rec/conf/focs/AndrewsAFKLL96"},
"url":"URL#5003062"
},
{
"@score":"1",
"@id":"5003063",
"info":{"authors":{"author":[{"@pid":"a/MatthewAndrews","text":"Matthew Andrews"},{"@pid":"b/MichaelABender","text":"Michael A. Bender"},{"@pid":"z/LisaZhang","text":"Lisa Zhang"}]},"title":"New Algorithms for the Disk Scheduling Problem.","venue":"FOCS","pages":"550-559","year":"1996","type":"Conference and Workshop Papers","key":"conf/focs/AndrewsBZ96","doi":"10.1109/SFCS.1996.548514","ee":"https://doi.org/10.1109/SFCS.1996.548514","url":"https://dblp.org/rec/conf/focs/AndrewsBZ96"},
"url":"URL#5003063"
},
{
"@score":"1",
"@id":"5003064",
"info":{"authors":{"author":[{"@pid":"a/LArge","text":"Lars Arge"},{"@pid":"v/JeffreyScottVitter","text":"Jeffrey Scott Vitter"}]},"title":"Optimal Dynamic Interval Management in External Memory (extended abstract).","venue":"FOCS","pages":"560-569","year":"1996","type":"Conference and Workshop Papers","key":"conf/focs/ArgeV96","doi":"10.1109/SFCS.1996.548515","ee":"https://doi.org/10.1109/SFCS.1996.548515","url":"https://dblp.org/rec/conf/focs/ArgeV96"},
"url":"URL#5003064"
},
{
"@score":"1",
"@id":"5003065",
"info":{"authors":{"author":[{"@pid":"24/5043","text":"Roy Armoni"},{"@pid":"s/MichaelESaks","text":"Michael E. Saks"},{"@pid":"w/AviWigderson","text":"Avi Wigderson"},{"@pid":"16/6590","text":"Shiyu Zhou"}]},"title":"Discrepancy Sets and Pseudorandom Generators for Combinatorial Rectangles.","venue":"FOCS","pages":"412-421","year":"1996","type":"Conference and Workshop Papers","key":"conf/focs/ArmoniSWZ96","doi":"10.1109/SFCS.1996.548500","ee":"https://doi.org/10.1109/SFCS.1996.548500","url":"https://dblp.org/rec/conf/focs/ArmoniSWZ96"},
"url":"URL#5003065"
},
{
"@score":"1",
"@id":"5003066",
"info":{"authors":{"author":{"@pid":"a/SArora","text":"Sanjeev Arora"}},"title":"Polynomial Time Approximation Schemes for Euclidean TSP and Other Geometric Problems.","venue":"FOCS","pages":"2-11","year":"1996","type":"Conference and Workshop Papers","key":"conf/focs/Arora96","doi":"10.1109/SFCS.1996.548458","ee":"https://doi.org/10.1109/SFCS.1996.548458","url":"https://dblp.org/rec/conf/focs/Arora96"},
"url":"URL#5003066"
},
{
"@score":"1",
"@id":"5003067",
"info":{"authors":{"author":[{"@pid":"a/SArora","text":"Sanjeev Arora"},{"@pid":"f/AlanMFrieze","text":"Alan M. Frieze"},{"@pid":"48/3950","text":"Haim Kaplan"}]},"title":"A New Rounding Procedure for the Assignment Problem with Applications to Dense Graph Arrangement Problems.","venue":"FOCS","pages":"21-30","year":"1996","type":"Conference and Workshop Papers","key":"conf/focs/AroraFK96","doi":"10.1109/SFCS.1996.548460","ee":"https://doi.org/10.1109/SFCS.1996.548460","url":"https://dblp.org/rec/conf/focs/AroraFK96"},
"url":"URL#5003067"
},
{
"@score":"1",
"@id":"5003068",
"info":{"authors":{"author":[{"@pid":"36/6115","text":"Yonatan Aumann"},{"@pid":"b/MichaelABender","text":"Michael A. Bender"}]},"title":"Fault Tolerant Data Structures.","venue":"FOCS","pages":"580-589","year":"1996","type":"Conference and Workshop Papers","key":"conf/focs/AumannB96","doi":"10.1109/SFCS.1996.548517","ee":"https://doi.org/10.1109/SFCS.1996.548517","url":"https://dblp.org/rec/conf/focs/AumannB96"},
"url":"URL#5003068"
},
{
"@score":"1",
"@id":"5003069",
"info":{"authors":{"author":{"@pid":"96/1036","text":"Yair Bartal"}},"title":"Probabilistic Approximations of Metric Spaces and Its Algorithmic Applications.","venue":"FOCS","pages":"184-193","year":"1996","type":"Conference and Workshop Papers","key":"conf/focs/Bartal96","doi":"10.1109/SFCS.1996.548477","ee":"https://doi.org/10.1109/SFCS.1996.548477","url":"https://dblp.org/rec/conf/focs/Bartal96"},
"url":"URL#5003069"
},
{
"@score":"1",
"@id":"5003070",
"info":{"authors":{"author":[{"@pid":"b/PaulBeame","text":"Paul Beame"},{"@pid":"p/TPitassi","text":"Toniann Pitassi"}]},"title":"Simplified and Improved Resolution Lower Bounds.","venue":"FOCS","pages":"274-282","year":"1996","type":"Conference and Workshop Papers","key":"conf/focs/BeameP96","doi":"10.1109/SFCS.1996.548486","ee":"https://doi.org/10.1109/SFCS.1996.548486","url":"https://dblp.org/rec/conf/focs/BeameP96"},
"url":"URL#5003070"
},
{
"@score":"1",
"@id":"5003071",
"info":{"authors":{"author":[{"@pid":"b/AmosBeimel","text":"Amos Beimel"},{"@pid":"37/1800","text":"Francesco Bergadano"},{"@pid":"b/NaderHBshouty","text":"Nader H. Bshouty"},{"@pid":"k/EyalKushilevitz","text":"Eyal Kushilevitz"},{"@pid":"61/649","text":"Stefano Varricchio"}]},"title":"On the Applications of Multiplicity Automata in Learning.","venue":"FOCS","pages":"349-358","year":"1996","type":"Conference and Workshop Papers","key":"conf/focs/BeimelBBKV96","doi":"10.1109/SFCS.1996.548494","ee":"https://doi.org/10.1109/SFCS.1996.548494","url":"https://dblp.org/rec/conf/focs/BeimelBBKV96"},
"url":"URL#5003071"
},
{
"@score":"1",
"@id":"5003072",
"info":{"authors":{"author":[{"@pid":"b/MBellare","text":"Mihir Bellare"},{"@pid":"c/RanCanetti","text":"Ran Canetti"},{"@pid":"46/6715","text":"Hugo Krawczyk"}]},"title":"Pseudorandom Functions Revisited - The Cascade Construction and Its Concrete Security.","venue":"FOCS","pages":"514-523","year":"1996","type":"Conference and Workshop Papers","key":"conf/focs/BellareCK96","doi":"10.1109/SFCS.1996.548510","ee":"https://doi.org/10.1109/SFCS.1996.548510","url":"https://dblp.org/rec/conf/focs/BellareCK96"},
"url":"URL#5003072"
},
{
"@score":"1",
"@id":"5003073",
"info":{"authors":{"author":[{"@pid":"b/AvrimBlum","text":"Avrim Blum"},{"@pid":"f/AlanMFrieze","text":"Alan M. Frieze"},{"@pid":"k/RaviKannan","text":"Ravi Kannan"},{"@pid":"v/SantoshVempala","text":"Santosh S. Vempala"}]},"title":"A Polynomial-Time Algorithm for Learning Noisy Linear Threshold Functions.","venue":"FOCS","pages":"330-338","year":"1996","type":"Conference and Workshop Papers","key":"conf/focs/BlumFKV96","doi":"10.1109/SFCS.1996.548492","ee":"https://doi.org/10.1109/SFCS.1996.548492","url":"https://dblp.org/rec/conf/focs/BlumFKV96"},
"url":"URL#5003073"
},
{
"@score":"1",
"@id":"5003074",
"info":{"authors":{"author":[{"@pid":"09/4301","text":"Andrei Z. Broder"},{"@pid":"f/AlanMFrieze","text":"Alan M. Frieze"},{"@pid":"u/EliUpfal","text":"Eli Upfal"}]},"title":"A General Approach to Dynamic Packet Routing with Bounded Buffers (extended abstract).","venue":"FOCS","pages":"390-399","year":"1996","type":"Conference and Workshop Papers","key":"conf/focs/BroderFU96","doi":"10.1109/SFCS.1996.548498","ee":"https://doi.org/10.1109/SFCS.1996.548498","url":"https://dblp.org/rec/conf/focs/BroderFU96"},
"url":"URL#5003074"
},
{
"@score":"1",
"@id":"5003075",
"info":{"authors":{"author":[{"@pid":"c/RanCanetti","text":"Ran Canetti"},{"@pid":"r/RosarioGennaro","text":"Rosario Gennaro"}]},"title":"Incoercible Multiparty Computation (extended abstract).","venue":"FOCS","pages":"504-513","year":"1996","type":"Conference and Workshop Papers","key":"conf/focs/CanettiG96","doi":"10.1109/SFCS.1996.548509","ee":"https://doi.org/10.1109/SFCS.1996.548509","url":"https://dblp.org/rec/conf/focs/CanettiG96"},
"url":"URL#5003075"
},
{
"@score":"1",
"@id":"5003076",
"info":{"authors":{"author":[{"@pid":"88/6502","text":"Prasad Chalasani"},{"@pid":"j/SomeshJha","text":"Somesh Jha"},{"@pid":"03/2296","text":"Isaac Saias"}]},"title":"Approximate Option Pricing.","venue":"FOCS","pages":"244-253","year":"1996","type":"Conference and Workshop Papers","key":"conf/focs/ChalasaniJS96","doi":"10.1109/SFCS.1996.548483","ee":"https://doi.org/10.1109/SFCS.1996.548483","url":"https://dblp.org/rec/conf/focs/ChalasaniJS96"},
"url":"URL#5003076"
},
{
"@score":"1",
"@id":"5003077",
"info":{"authors":{"author":[{"@pid":"87/5654","text":"Joseph Cheriyan"},{"@pid":"t/RThurimella","text":"Ramakrishna Thurimella"}]},"title":"Approximating Minimum-Size k-Connected Spanning Subgraphs via Matching (extended abstract).","venue":"FOCS","pages":"292-301","year":"1996","type":"Conference and Workshop Papers","key":"conf/focs/CheriyanT96","doi":"10.1109/SFCS.1996.548488","ee":"https://doi.org/10.1109/SFCS.1996.548488","url":"https://dblp.org/rec/conf/focs/CheriyanT96"},
"url":"URL#5003077"
},
{
"@score":"1",
"@id":"5003078",
"info":{"authors":{"author":{"@pid":"c/ThomasMCover","text":"Thomas M. Cover"}},"title":"Universal Data Compression and Portfolio Selection.","venue":"FOCS","pages":"534-538","year":"1996","type":"Conference and Workshop Papers","key":"conf/focs/Cover96","doi":"10.1109/SFCS.1996.548512","ee":"https://doi.org/10.1109/SFCS.1996.548512","url":"https://dblp.org/rec/conf/focs/Cover96"},
"url":"URL#5003078"
},
{
"@score":"1",
"@id":"5003079",
"info":{"authors":{"author":[{"@pid":"92/271","text":"William H. Cunningham"},{"@pid":"47/2555","text":"James F. Geelen"}]},"title":"The Optimal Path-Matching Problem.","venue":"FOCS","pages":"78-85","year":"1996","type":"Conference and Workshop Papers","key":"conf/focs/CunninghamG96","doi":"10.1109/SFCS.1996.548466","ee":"https://doi.org/10.1109/SFCS.1996.548466","url":"https://dblp.org/rec/conf/focs/CunninghamG96"},
"url":"URL#5003079"
},
{
"@score":"1",
"@id":"5003080",
"info":{"authors":{"author":[{"@pid":"89/2082","text":"Dorit Dor"},{"@pid":"49/6683","text":"Shay Halperin"},{"@pid":"z/UriZwick","text":"Uri Zwick"}]},"title":"All Pairs Almost Shortest Paths.","venue":"FOCS","pages":"452-461","year":"1996","type":"Conference and Workshop Papers","key":"conf/focs/DorHZ96","doi":"10.1109/SFCS.1996.548504","ee":"https://doi.org/10.1109/SFCS.1996.548504","url":"https://dblp.org/rec/conf/focs/DorHZ96"},
"url":"URL#5003080"
},
{
"@score":"1",
"@id":"5003081",
"info":{"authors":{"author":[{"@pid":"89/2082","text":"Dorit Dor"},{"@pid":"z/UriZwick","text":"Uri Zwick"}]},"title":"Median Selection Requires (2+epsilon)n Comparisons.","venue":"FOCS","pages":"125-134","year":"1996","type":"Conference and Workshop Papers","key":"conf/focs/DorZ96","doi":"10.1109/SFCS.1996.548471","ee":"https://doi.org/10.1109/SFCS.1996.548471","url":"https://dblp.org/rec/conf/focs/DorZ96"},
"url":"URL#5003081"
},
{
"@score":"1",
"@id":"5003082",
"info":{"authors":{"author":[{"@pid":"d/ChristophDurr","text":"Christoph Dürr"},{"@pid":"18/3053","text":"Miklos Santha"}]},"title":"A Decision Procedure for Unitary Linear Quantum Cellular Automata.","venue":"FOCS","pages":"38-45","year":"1996","type":"Conference and Workshop Papers","key":"conf/focs/DurrS96","doi":"10.1109/SFCS.1996.548462","ee":"https://doi.org/10.1109/SFCS.1996.548462","url":"https://dblp.org/rec/conf/focs/DurrS96"},
"url":"URL#5003082"
},
{
"@score":"1",
"@id":"5003083",
"info":{"authors":{"author":[{"@pid":"e/FundaErgun","text":"Funda Ergün"},{"@pid":"k/RaviKumar","text":"Ravi Kumar 0001"},{"@pid":"r/RonittRubinfeld","text":"Ronitt Rubinfeld"}]},"title":"Approximate Checking of Polynomials and Functional Equations (extended abstract).","venue":"FOCS","pages":"592-601","year":"1996","type":"Conference and Workshop Papers","key":"conf/focs/ErgunKR96","doi":"10.1109/SFCS.1996.548518","ee":"https://doi.org/10.1109/SFCS.1996.548518","url":"https://dblp.org/rec/conf/focs/ErgunKR96"},
"url":"URL#5003083"
},
{
"@score":"1",
"@id":"5003084",
"info":{"authors":{"author":{"@pid":"e/JeffErickson","text":"Jeff Erickson 0001"}},"title":"Better Lower Bounds for Halfspace Emptiness.","venue":"FOCS","pages":"472-481","year":"1996","type":"Conference and Workshop Papers","key":"conf/focs/Erickson96","doi":"10.1109/SFCS.1996.548506","ee":"https://doi.org/10.1109/SFCS.1996.548506","url":"https://dblp.org/rec/conf/focs/Erickson96"},
"url":"URL#5003084"
},
{
"@score":"1",
"@id":"5003085",
"info":{"authors":{"author":[{"@pid":"e/OEtzioni","text":"Oren Etzioni"},{"@pid":"56/2425","text":"Steve Hanks"},{"@pid":"j/TaoJiang-1","text":"Tao Jiang 0001"},{"@pid":"k/RichardMKarp","text":"Richard M. Karp"},{"@pid":"82/1151","text":"Omid Madani"},{"@pid":"52/6367","text":"Orli Waarts"}]},"title":"Efficient Information Gathering on the Internet (extended abstract).","venue":"FOCS","pages":"234-243","year":"1996","type":"Conference and Workshop Papers","key":"conf/focs/EtzioniHJKMW96","doi":"10.1109/SFCS.1996.548482","ee":"https://doi.org/10.1109/SFCS.1996.548482","url":"https://dblp.org/rec/conf/focs/EtzioniHJKMW96"},
"url":"URL#5003085"
},
{
"@score":"1",
"@id":"5003086",
"info":{"authors":{"author":[{"@pid":"45/1790","text":"Guy Even"},{"@pid":"n/JosephNaor","text":"Joseph Naor"},{"@pid":"83/2790","text":"Leonid Zosin"}]},"title":"An 8-Approximation Algorithm for the Subset Feedback Vertex Set Problem.","venue":"FOCS","pages":"310-319","year":"1996","type":"Conference and Workshop Papers","key":"conf/focs/EvenNZ96","doi":"10.1109/SFCS.1996.548490","ee":"https://doi.org/10.1109/SFCS.1996.548490","url":"https://dblp.org/rec/conf/focs/EvenNZ96"},
"url":"URL#5003086"
},
{
"@score":"1",
"@id":"5003087",
"info":{"authors":{"author":[{"@pid":"f/AlanMFrieze","text":"Alan M. Frieze"},{"@pid":"j/MarkJerrum","text":"Mark Jerrum"},{"@pid":"k/RaviKannan","text":"Ravi Kannan"}]},"title":"Learning Linear Transformations.","venue":"FOCS","pages":"359-368","year":"1996","type":"Conference and Workshop Papers","key":"conf/focs/FriezeJK96","doi":"10.1109/SFCS.1996.548495","ee":"https://doi.org/10.1109/SFCS.1996.548495","url":"https://dblp.org/rec/conf/focs/FriezeJK96"},
"url":"URL#5003087"
},
{
"@score":"1",
"@id":"5003088",
"info":{"authors":{"author":[{"@pid":"f/AlanMFrieze","text":"Alan M. Frieze"},{"@pid":"k/RaviKannan","text":"Ravi Kannan"}]},"title":"The Regularity Lemma and Approximation Schemes for Dense Problems.","venue":"FOCS","pages":"12-20","year":"1996","type":"Conference and Workshop Papers","key":"conf/focs/FriezeK96","doi":"10.1109/SFCS.1996.548459","ee":"https://doi.org/10.1109/SFCS.1996.548459","url":"https://dblp.org/rec/conf/focs/FriezeK96"},
"url":"URL#5003088"
},
{
"@score":"1",
"@id":"5003089",
"info":{"authors":{"author":{"@pid":"g/NaveenGarg","text":"Naveen Garg 0001"}},"title":"A 3-Approximation for the Minimum Tree Spanning k Vertices.","venue":"FOCS","pages":"302-309","year":"1996","type":"Conference and Workshop Papers","key":"conf/focs/Garg96","doi":"10.1109/SFCS.1996.548489","ee":"https://doi.org/10.1109/SFCS.1996.548489","url":"https://dblp.org/rec/conf/focs/Garg96"},
"url":"URL#5003089"
},
{
"@score":"1",
"@id":"5003090",
"info":{"authors":{"author":[{"@pid":"g/OdedGoldreich","text":"Oded Goldreich 0001"},{"@pid":"g/ShafiGoldwasser","text":"Shafi Goldwasser"},{"@pid":"85/4800","text":"Dana Ron"}]},"title":"Property Testing and Its Connection to Learning and Approximation.","venue":"FOCS","pages":"339-348","year":"1996","type":"Conference and Workshop Papers","key":"conf/focs/GoldreichGR96","doi":"10.1109/SFCS.1996.548493","ee":"https://doi.org/10.1109/SFCS.1996.548493","url":"https://dblp.org/rec/conf/focs/GoldreichGR96"},
"url":"URL#5003090"
},
{
"@score":"1",
"@id":"5003091",
"info":{"authors":{"author":{"@pid":"g/MGrohe","text":"Martin Grohe"}},"title":"Equivalence in Finite-Variable Logics is Complete for Polynomial Time.","venue":"FOCS","pages":"264-273","year":"1996","type":"Conference and Workshop Papers","key":"conf/focs/Grohe96","doi":"10.1109/SFCS.1996.548485","ee":"https://doi.org/10.1109/SFCS.1996.548485","url":"https://dblp.org/rec/conf/focs/Grohe96"},
"url":"URL#5003091"
},
{
"@score":"1",
"@id":"5003092",
"info":{"authors":{"author":{"@pid":"47/3155","text":"Johan Håstad"}},"title":"Clique is Hard to Approximate Within n1-epsilon.","venue":"FOCS","pages":"627-636","year":"1996","type":"Conference and Workshop Papers","key":"conf/focs/Hastad96","doi":"10.1109/SFCS.1996.548522","ee":"https://doi.org/10.1109/SFCS.1996.548522","url":"https://dblp.org/rec/conf/focs/Hastad96"},
"url":"URL#5003092"
},
{
"@score":"1",
"@id":"5003093",
"info":{"authors":{"author":[{"@pid":"h/FMaufderHeide","text":"Friedhelm Meyer auf der Heide"},{"@pid":"s/ChristianScheideler","text":"Christian Scheideler"}]},"title":"Deterministic Routing with Bounded Buffers - Turning Offline into Online Protocols.","venue":"FOCS","pages":"370-379","year":"1996","type":"Conference and Workshop Papers","key":"conf/focs/HeideS96","doi":"10.1109/SFCS.1996.548496","ee":"https://doi.org/10.1109/SFCS.1996.548496","url":"https://dblp.org/rec/conf/focs/HeideS96"},
"url":"URL#5003093"
},
{
"@score":"1",
"@id":"5003094",
"info":{"authors":{"author":[{"@pid":"h/MonikaRauchHenzinger","text":"Monika Rauch Henzinger"},{"@pid":"r/SRao","text":"Satish Rao"},{"@pid":"g/HaroldNGabow","text":"Harold N. Gabow"}]},"title":"Computing Vertex Connectivity - New Bounds from Old Techniques.","venue":"FOCS","pages":"462-471","year":"1996","type":"Conference and Workshop Papers","key":"conf/focs/HenzingerRG96","doi":"10.1109/SFCS.1996.548505","ee":"https://doi.org/10.1109/SFCS.1996.548505","url":"https://dblp.org/rec/conf/focs/HenzingerRG96"},
"url":"URL#5003094"
},
{
"@score":"1",
"@id":"5003095",
"info":{"authors":{"author":[{"@pid":"41/9","text":"Ming-Deh A. Huang"},{"@pid":"44/6835","text":"Yiu-Chung Wong"}]},"title":"Solving Systems of Polynomial Congruences Modulo a Large Prime (extended abstract).","venue":"FOCS","pages":"115-124","year":"1996","type":"Conference and Workshop Papers","key":"conf/focs/HuangW96","doi":"10.1109/SFCS.1996.548470","ee":"https://doi.org/10.1109/SFCS.1996.548470","url":"https://dblp.org/rec/conf/focs/HuangW96"},
"url":"URL#5003095"
},
{
"@score":"1",
"@id":"5003096",
"info":{"authors":{"author":[{"@pid":"k/RaviKannan","text":"Ravi Kannan"},{"@pid":"22/4405","text":"Guangxing Li"}]},"title":"Sampling According to the Multivariate Normal Density.","venue":"FOCS","pages":"204-212","year":"1996","type":"Conference and Workshop Papers","key":"conf/focs/KannanL96","doi":"10.1109/SFCS.1996.548479","ee":"https://doi.org/10.1109/SFCS.1996.548479","url":"https://dblp.org/rec/conf/focs/KannanL96"},
"url":"URL#5003096"
},
{
"@score":"1",
"@id":"5003097",
"info":{"authors":{"author":[{"@pid":"k/ClaireKenyon","text":"Claire Kenyon"},{"@pid":"36/2063","text":"Eric Rémila"}]},"title":"Approximate Strip Packing.","venue":"FOCS","pages":"31-36","year":"1996","type":"Conference and Workshop Papers","key":"conf/focs/KenyonR96","doi":"10.1109/SFCS.1996.548461","ee":"https://doi.org/10.1109/SFCS.1996.548461","url":"https://dblp.org/rec/conf/focs/KenyonR96"},
"url":"URL#5003097"
},
{
"@score":"1",
"@id":"5003098",
"info":{"authors":{"author":[{"@pid":"38/3022","text":"Tracy Kimbrel"},{"@pid":"k/AnnaRKarlin","text":"Anna R. Karlin"}]},"title":"Near-Optimal Parallel Prefetching and Caching.","venue":"FOCS","pages":"540-549","year":"1996","type":"Conference and Workshop Papers","key":"conf/focs/KimbrelK96","doi":"10.1109/SFCS.1996.548513","ee":"https://doi.org/10.1109/SFCS.1996.548513","url":"https://dblp.org/rec/conf/focs/KimbrelK96"},
"url":"URL#5003098"
},
{
"@score":"1",
"@id":"5003099",
"info":{"authors":{"author":{"@pid":"k/JonMKleinberg","text":"Jon M. Kleinberg"}},"title":"Single-Source Unsplittable Flow.","venue":"FOCS","pages":"68-77","year":"1996","type":"Conference and Workshop Papers","key":"conf/focs/Kleinberg96","doi":"10.1109/SFCS.1996.548465","ee":"https://doi.org/10.1109/SFCS.1996.548465","url":"https://dblp.org/rec/conf/focs/Kleinberg96"},
"url":"URL#5003099"
},
{
"@score":"1",
"@id":"5003100",
"info":{"authors":{"author":[{"@pid":"k/JonMKleinberg","text":"Jon M. Kleinberg"},{"@pid":"r/RonittRubinfeld","text":"Ronitt Rubinfeld"}]},"title":"Short Paths in Expander Graphs.","venue":"FOCS","pages":"86-95","year":"1996","type":"Conference and Workshop Papers","key":"conf/focs/KleinbergR96","doi":"10.1109/SFCS.1996.548467","ee":"https://doi.org/10.1109/SFCS.1996.548467","url":"https://dblp.org/rec/conf/focs/KleinbergR96"},
"url":"URL#5003100"
},
{
"@score":"1",
"@id":"5003101",
"info":{"authors":{"author":{"@pid":"33/941","text":"Grigory Kogan"}},"title":"Computing Permanents over Fields of Characteristic 3 - Where and Why It Becomes Difficult (extended abstract).","venue":"FOCS","pages":"108-114","year":"1996","type":"Conference and Workshop Papers","key":"conf/focs/Kogan96","doi":"10.1109/SFCS.1996.548469","ee":"https://doi.org/10.1109/SFCS.1996.548469","url":"https://dblp.org/rec/conf/focs/Kogan96"},
"url":"URL#5003101"
},
{
"@score":"1",
"@id":"5003102",
"info":{"authors":{"author":[{"@pid":"k/RaviKumar","text":"Ravi Kumar 0001"},{"@pid":"77/5746","text":"D. Sivakumar"}]},"title":"Efficient Self-Testing/Self-Correction of Linear Recurrences.","venue":"FOCS","pages":"602-611","year":"1996","type":"Conference and Workshop Papers","key":"conf/focs/KumarS96","doi":"10.1109/SFCS.1996.548519","ee":"https://doi.org/10.1109/SFCS.1996.548519","url":"https://dblp.org/rec/conf/focs/KumarS96"},
"url":"URL#5003102"
},
{
"@score":"1",
"@id":"5003103",
"info":{"authors":{"author":[{"@pid":"29/5675","text":"Neal Madras"},{"@pid":"62/3610","text":"Dana Randall"}]},"title":"Factoring Graphs to Bound Mixing Rates.","venue":"FOCS","pages":"194-203","year":"1996","type":"Conference and Workshop Papers","key":"conf/focs/MadrasR96","doi":"10.1109/SFCS.1996.548478","ee":"https://doi.org/10.1109/SFCS.1996.548478","url":"https://dblp.org/rec/conf/focs/MadrasR96"},
"url":"URL#5003103"
},
{
"@score":"1",
"@id":"5003104",
"info":{"authors":{"author":{"@pid":"74/838","text":"Michael Mitzenmacher"}},"title":"Load Balancing and Density Dependent Jump Markov Processes (extended abstract).","venue":"FOCS","pages":"213-222","year":"1996","type":"Conference and Workshop Papers","key":"conf/focs/Mitzenmacher96","doi":"10.1109/SFCS.1996.548480","ee":"https://doi.org/10.1109/SFCS.1996.548480","url":"https://dblp.org/rec/conf/focs/Mitzenmacher96"},
"url":"URL#5003104"
},
{
"@score":"1",
"@id":"5003105",
"info":{"authors":{"author":[{"@pid":"29/3287","text":"Erez Petrank"},{"@pid":"t/GaborTardos","text":"Gábor Tardos"}]},"title":"On the Knowledge Complexity of NP.","venue":"FOCS","pages":"494-503","year":"1996","type":"Conference and Workshop Papers","key":"conf/focs/PetrankT96","doi":"10.1109/SFCS.1996.548508","ee":"https://doi.org/10.1109/SFCS.1996.548508","url":"https://dblp.org/rec/conf/focs/PetrankT96"},
"url":"URL#5003105"
},
{
"@score":"1",
"@id":"5003106",
"info":{"authors":{"author":[{"@pid":"p/CGPlaxton","text":"C. Greg Plaxton"},{"@pid":"r/RRajaraman","text":"Rajmohan Rajaraman"}]},"title":"Fast Fault-Tolerant Concurrent Access to Shared Objects.","venue":"FOCS","pages":"570-579","year":"1996","type":"Conference and Workshop Papers","key":"conf/focs/PlaxtonR96","doi":"10.1109/SFCS.1996.548516","ee":"https://doi.org/10.1109/SFCS.1996.548516","url":"https://dblp.org/rec/conf/focs/PlaxtonR96"},
"url":"URL#5003106"
},
{
"@score":"1",
"@id":"5003107",
"info":{"authors":{"author":{"@pid":"r/YRabani","text":"Yuval Rabani"}},"title":"Path Coloring on the Mesh.","venue":"FOCS","pages":"400-409","year":"1996","type":"Conference and Workshop Papers","key":"conf/focs/Rabani96","doi":"10.1109/SFCS.1996.548499","ee":"https://doi.org/10.1109/SFCS.1996.548499","url":"https://dblp.org/rec/conf/focs/Rabani96"},
"url":"URL#5003107"
},
{
"@score":"1",
"@id":"5003108",
"info":{"authors":{"author":{"@pid":"r/MORabin","text":"Michael O. Rabin"}},"title":"Computationally Hard Algebraic Problems (extended abstract).","venue":"FOCS","pages":"284-289","year":"1996","type":"Conference and Workshop Papers","key":"conf/focs/Rabin96","doi":"10.1109/SFCS.1996.548487","ee":"https://doi.org/10.1109/SFCS.1996.548487","url":"https://dblp.org/rec/conf/focs/Rabin96"},
"url":"URL#5003108"
},
{
"@score":"1",
"@id":"5003109",
"info":{"authors":{"author":[{"@pid":"76/717","text":"Sridhar Rajagopalan"},{"@pid":"53/4745","text":"Leonard J. Schulman"}]},"title":"Verifying Identities (extended abstract).","venue":"FOCS","pages":"612-616","year":"1996","type":"Conference and Workshop Papers","key":"conf/focs/RajagopalanS96","doi":"10.1109/SFCS.1996.548520","ee":"https://doi.org/10.1109/SFCS.1996.548520","url":"https://dblp.org/rec/conf/focs/RajagopalanS96"},
"url":"URL#5003109"
},
{
"@score":"1",
"@id":"5003110",
"info":{"authors":{"author":[{"@pid":"s/SCSahinalp","text":"Süleyman Cenk Sahinalp"},{"@pid":"v/UziVishkin","text":"Uzi Vishkin"}]},"title":"Efficient Approximate and Dynamic Matching of Patterns Using a Labeling Paradigm (extended abstract).","venue":"FOCS","pages":"320-328","year":"1996","type":"Conference and Workshop Papers","key":"conf/focs/SahinalpV96","doi":"10.1109/SFCS.1996.548491","ee":"https://doi.org/10.1109/SFCS.1996.548491","url":"https://dblp.org/rec/conf/focs/SahinalpV96"},
"url":"URL#5003110"
},
{
"@score":"1",
"@id":"5003111",
"info":{"authors":{"author":{"@pid":"s/PeterWShor","text":"Peter W. Shor"}},"title":"Fault-Tolerant Quantum Computation.","venue":"FOCS","pages":"56-65","year":"1996","type":"Conference and Workshop Papers","key":"conf/focs/Shor96","doi":"10.1109/SFCS.1996.548464","ee":"https://doi.org/10.1109/SFCS.1996.548464","url":"https://dblp.org/rec/conf/focs/Shor96"},
"url":"URL#5003111"
},
{
"@score":"1",
"@id":"5003112",
"info":{"authors":{"author":{"@pid":"s/DanielASpielman","text":"Daniel A. Spielman"}},"title":"Highly Fault-Tolerant Parallel Computation (extended abstract).","venue":"FOCS","pages":"154-163","year":"1996","type":"Conference and Workshop Papers","key":"conf/focs/Spielman96","doi":"10.1109/SFCS.1996.548474","ee":"https://doi.org/10.1109/SFCS.1996.548474","url":"https://dblp.org/rec/conf/focs/Spielman96"},
"url":"URL#5003112"
},
{
"@score":"1",
"@id":"5003113",
"info":{"authors":{"author":[{"@pid":"s/DanielASpielman","text":"Daniel A. Spielman"},{"@pid":"t/ShangHuaTeng","text":"Shang-Hua Teng"}]},"title":"Spectral Partitioning Works - Planar Graphs and Finite Element Meshes.","venue":"FOCS","pages":"96-105","year":"1996","type":"Conference and Workshop Papers","key":"conf/focs/SpielmanT96","doi":"10.1109/SFCS.1996.548468","ee":"https://doi.org/10.1109/SFCS.1996.548468","url":"https://dblp.org/rec/conf/focs/SpielmanT96"},
"url":"URL#5003113"
},
{
"@score":"1",
"@id":"5003114",
"info":{"authors":{"author":{"@pid":"s/MadhuSudan","text":"Madhu Sudan"}},"title":"Maximum Likelihood Decoding of Reed Solomon Codes.","venue":"FOCS","pages":"164-172","year":"1996","type":"Conference and Workshop Papers","key":"conf/focs/Sudan96","doi":"10.1109/SFCS.1996.548475","ee":"https://doi.org/10.1109/SFCS.1996.548475","url":"https://dblp.org/rec/conf/focs/Sudan96"},
"url":"URL#5003114"
},
{
"@score":"1",
"@id":"5003115",
"info":{"authors":{"author":[{"@pid":"t/DenisTherien","text":"Denis Thérien"},{"@pid":"w/ThomasWilke","text":"Thomas Wilke"}]},"title":"Temporal Logic and Semidirect Products - An Effective Characterization of the Until Hierarchy.","venue":"FOCS","pages":"256-263","year":"1996","type":"Conference and Workshop Papers","key":"conf/focs/TherienW96","doi":"10.1109/SFCS.1996.548484","ee":"https://doi.org/10.1109/SFCS.1996.548484","url":"https://dblp.org/rec/conf/focs/TherienW96"},
"url":"URL#5003115"
},
{
"@score":"1",
"@id":"5003116",
"info":{"authors":{"author":[{"@pid":"t/LucaTrevisan","text":"Luca Trevisan"},{"@pid":"60/1574","text":"Gregory B. Sorkin"},{"@pid":"s/MadhuSudan","text":"Madhu Sudan"},{"@pid":"w/DavidPWilliamson","text":"David P. Williamson"}]},"title":"Gadgets, Approximation, and Linear Programming (extended abstract).","venue":"FOCS","pages":"617-626","year":"1996","type":"Conference and Workshop Papers","key":"conf/focs/TrevisanSSW96","doi":"10.1109/SFCS.1996.548521","ee":"https://doi.org/10.1109/SFCS.1996.548521","url":"https://dblp.org/rec/conf/focs/TrevisanSSW96"},
"url":"URL#5003116"
},
{
"@score":"1",
"@id":"5003117",
"info":{"authors":{"author":[{"@pid":"84/5806","text":"Vijay V. Vazirani"},{"@pid":"s/HuzurSaran","text":"Huzur Saran"},{"@pid":"r/BSundarRajan","text":"B. Sundar Rajan"}]},"title":"An Efficient Algorithm for Constructing Minimal Trellises for Codes over Finite Abelian Groups.","venue":"FOCS","pages":"144-153","year":"1996","type":"Conference and Workshop Papers","key":"conf/focs/VaziraniSR96","doi":"10.1109/SFCS.1996.548473","ee":"https://doi.org/10.1109/SFCS.1996.548473","url":"https://dblp.org/rec/conf/focs/VaziraniSR96"},
"url":"URL#5003117"
},
{
"@score":"1",
"@id":"5020714",
"info":{"title":"37th Annual Symposium on Foundations of Computer Science, FOCS &apos;96, Burlington, Vermont, USA, 14-16 October, 1996","venue":"FOCS","publisher":"IEEE Computer Society","year":"1996","type":"Editorship","key":"conf/focs/1996","ee":"https://ieeexplore.ieee.org/xpl/conhome/4141/proceeding","url":"https://dblp.org/rec/conf/focs/1996"},
"url":"URL#5020714"
}
]
}
}
}
